[
  {
    "id": "1280675",
    "winery_full": "Dominus Estate",
    "wine_full": "Napa Valley",
    "vintage": "2018",
    "note": "This is tightly packed, with sleek, pure, driven notes of cassis, plum reduction and blackberry puree allied to an iron spine, while subtle alder, juniper, sweet bay leaf and tobacco notes peek in throughout. Very fine-grained, but impressively sturdy in feel, with a long, lingering note of iron piercing the finish. For the cellar. Cabernet Sauvignon, Cabernet Franc and Petit Verdot. Best from 2024 through 2040. 4,000 cases made.",
    "taster_initials": "JM",
    "color": "Red",
    "country": "United States",
    "region": "Napa",
    "score": 97,
    "price": 269,
    "alternate_bottle_size": "",
    "issue_date": "44500",
    "top100_year": 2021,
    "top100_rank": 1,
    "label_url": "https://mshanken-wineapi.imgix.net/Dominus%20Estate/Napa%20Valley/2018/a3910ffb319f293aa7a1dc7b203c65c4",
    "wine_type": "still"
  },
  {
    "id": "1271945",
    "winery_full": "Château Pichon Longueville Lalande",
    "wine_full": "Pauillac",
    "vintage": "2018",
    "note": "Offers a deep well of dark currant, blackberry paste and plum preserves fruit that needs time to unwind fully, as it’s shrouded in warm earth, tobacco, singed cedar, sweet bay leaf and savory notes. A ramrod of graphite adds to the strident, structured feel. Cabernet Sauvignon, Merlot, Cabernet Franc and Petit Verdot. Best from 2030 through 2050. 13,000 cases made.",
    "taster_initials": "JM",
    "color": "Red",
    "country": "France",
    "region": "Left Bank",
    "score": 98,
    "price": 198,
    "alternate_bottle_size": "",
    "issue_date": "44286",
    "top100_year": 2021,
    "top100_rank": 2,
    "label_url": "https://mshanken-wineapi.imgix.net/Ch%C3%A2teau%20Pichon%20Longueville%20Lalande/Pauillac/2018/58a9d19e1129d403ee3b8923211d0125",
    "wine_type": "still"
  },
  {
    "id": "1282770",
    "winery_full": "Heitz",
    "wine_full": "Cabernet Sauvignon Oakville Martha's Vineyard",
    "vintage": "2016",
    "note": "This throws off an overt and alluring mint aroma, while sweet bay leaf, violet, damson plum, red tea and steeped <em>griotte</em> notes all glide through together, carried by remarkably fine-grained tannins. Ends with a gentle echo of mint on the finish, while a subtle minerality chimes through as well. A stylish and suave wine, with plenty of charm now, but also pristine balance for cellaring. Best from 2022 through 2038. 2,500 cases made.",
    "taster_initials": "JM",
    "color": "Red",
    "country": "United States",
    "region": "Napa",
    "score": 95,
    "price": 250,
    "alternate_bottle_size": "",
    "issue_date": "44515",
    "top100_year": 2021,
    "top100_rank": 3,
    "label_url": "https://mshanken-wineapi.imgix.net/Heitz/Cabernet%20Sauvignon%20Oakville%20Martha%27s%20Vineyard/2016/6af689e17b18835c281b3a63ccbf3036",
    "wine_type": "still"
  },
  {
    "id": "1277232",
    "winery_full": "Merum Priorati",
    "wine_full": "Priorat Destí",
    "vintage": "2018",
    "note": "Refined and elegant, this concentrated red shows cherry, violet and anise notes, with expressive mineral undertones that give it finesse. Elements of mountain herb and spice echo through the finish. Grenache, Carignan and Syrah. Drink now through 2033. 14,000 cases made, 1,600 cases imported.",
    "taster_initials": "GS",
    "color": "Red",
    "country": "Spain",
    "region": "Spain",
    "score": 95,
    "price": 49,
    "alternate_bottle_size": "",
    "issue_date": "44439",
    "top100_year": 2021,
    "top100_rank": 4,
    "label_url": "https://mshanken-wineapi.imgix.net/Merum%20Priorati/Priorat%20Dest%C3%AD/2018/d3a55fc0f12a5f82ccb1219ea782b0b6",
    "wine_type": "still"
  },
  {
    "id": "1275621",
    "winery_full": "Le Chiuse",
    "wine_full": "Brunello di Montalcino",
    "vintage": "2016",
    "note": "Pretty strawberry, currant and cherry flavors take center stage in this taut and linear red, flanked by floral, mineral and tobacco notes, with fine balance and intensity on a slim frame. This is ample, yet the refined tannins provide structure. Best from 2024 through 2048. 15,000 cases made, 1,000 cases imported.",
    "taster_initials": "BS",
    "color": "Red",
    "country": "Italy",
    "region": "Tuscany",
    "score": 98,
    "price": 99,
    "alternate_bottle_size": "",
    "issue_date": "44377",
    "top100_year": 2021,
    "top100_rank": 5,
    "label_url": "https://mshanken-wineapi.imgix.net/Le%20Chiuse/Brunello%20di%20Montalcino/2016/9b31b8c14d813fa8de709668568b23af",
    "wine_type": "still"
  },
  {
    "id": "1274648",
    "winery_full": "Louis Latour",
    "wine_full": "Corton-Charlemagne",
    "vintage": "2018",
    "note": "Fresh and fruity, with aromas and flavors of lemon, pear, white flowers and stone, showing great tension and an underlying mineral component that gives this energy and length. The lemon theme continues on the lingering aftertaste, along with butter and pastry accents. Best from 2022 through 2029. 2,702 cases made, 1,200 cases imported.",
    "taster_initials": "BS",
    "color": "White",
    "country": "France",
    "region": "Côte de Beaune",
    "score": 95,
    "price": 200,
    "alternate_bottle_size": "",
    "issue_date": "44408",
    "top100_year": 2021,
    "top100_rank": 6,
    "label_url": "https://mshanken-wineapi.imgix.net/Louis%20Latour/Corton-Charlemagne/2018/4e50d86d49a6aa5f644c4e1424d09b92",
    "wine_type": "still"
  },
  {
    "id": "1272717",
    "winery_full": "Château Léoville Poyferré",
    "wine_full": "St.-Julien",
    "vintage": "2018",
    "note": "Waves of warmed cassis, mocha and warm tar aromas lead the way, while the core of macerated plum, blackberry and blueberry fruit waits its turn, showing admirable breadth and depth when it arrives, with roasted apple wood, bramble and cast iron buried deeply through the finish. This is a powerfully rendered wine with a cashmere scarf as accent. Cabernet Sauvignon, Merlot, Cabernet Franc and Petit Verdot. Best from 2024 through 2040. 15,000 cases made.",
    "taster_initials": "JM",
    "color": "Red",
    "country": "France",
    "region": "Left Bank",
    "score": 97,
    "price": 104,
    "alternate_bottle_size": "",
    "issue_date": "44286",
    "top100_year": 2021,
    "top100_rank": 7,
    "label_url": "https://mshanken-wineapi.imgix.net/Ch%C3%A2teau%20L%C3%A9oville%20Poyferr%C3%A9/St.-Julien/2018/8d4fe0d08db1ad3b40db971535da7760",
    "wine_type": "still"
  },
  {
    "id": "1270892",
    "winery_full": "Cavallotto",
    "wine_full": "Barolo Bricco Boschis",
    "vintage": "2016",
    "note": "The core of cherry and currant is framed by notes of hay, eucalyptus and wild thyme, with a solid structure that leaves a dusty feel, offset by the sweet, ripe fruit. Balanced overall, this is  built for the long haul. Best from 2023 through 2045. 3,100 cases made, 1,000 cases imported.",
    "taster_initials": "BS",
    "color": "Red",
    "country": "Italy",
    "region": "Piedmont",
    "score": 95,
    "price": 90,
    "alternate_bottle_size": "",
    "issue_date": "44286",
    "top100_year": 2021,
    "top100_rank": 8,
    "label_url": "https://mshanken-wineapi.imgix.net/Cavallotto/Barolo%20Bricco%20Boschis/2016/6484643e9c8bcaf8d3b7393ac241a424",
    "wine_type": "still"
  },
  {
    "id": "1277441",
    "winery_full": "Salvestrin",
    "wine_full": "Cabernet Sauvignon St. Helena Dr. Crane Vineyard",
    "vintage": "2018",
    "note": "Bright and fresh, with lots of red currant, plum and black cherry fruit notes driving along nicely, while a subtle tug of iron runs underneath. Late floral and warm earth flashes on the finish add more range and contrast. Focused, detailed and really well built. To be released October 2021. Best from 2022 through 2035. 1,260 cases made.",
    "taster_initials": "JM",
    "color": "Red",
    "country": "United States",
    "region": "Napa",
    "score": 95,
    "price": 80,
    "alternate_bottle_size": "",
    "issue_date": "44439",
    "top100_year": 2021,
    "top100_rank": 9,
    "label_url": "https://mshanken-wineapi.imgix.net/Salvestrin/Cabernet%20Sauvignon%20St.%20Helena%20Dr.%20Crane%20Vineyard/2018/9156eb958450e9ebfcfba30c2ba43119",
    "wine_type": "still"
  },
  {
    "id": "1283260",
    "winery_full": "Château de Nalys",
    "wine_full": "Châteauneuf-du-Pape",
    "vintage": "2018",
    "note": "A bright savory note leads off this red, followed quickly by sanguine and bay leaf accents, all melding nicely with the core of steeped blackberry, raspberry and plum fruit flavors as they move through the rich, licorice root–tinged finish. Best from 2022 through 2035. 1,000 cases imported.",
    "taster_initials": "JM",
    "color": "Red",
    "country": "France",
    "region": "Southern Rhône",
    "score": 95,
    "price": 105,
    "alternate_bottle_size": "",
    "issue_date": "44545",
    "top100_year": 2021,
    "top100_rank": 10,
    "label_url": "https://mshanken-wineapi.imgix.net/Ch%C3%A2teau%20de%20Nalys/Ch%C3%A2teauneuf-du-Pape/2018/73b1ecb2a68759f23341936d4be6686c",
    "wine_type": "still"
  },
  {
    "id": "1276832",
    "winery_full": "Aubert",
    "wine_full": "Chardonnay Russian River Valley Eastside",
    "vintage": "2019",
    "note": "This sings with rich toastiness to the ripe, juicy and powerfully structured white fruit and cooking spice flavors that are backed by firm acidity. Buttery midpalate, with a glistening finish that shows accents of dried tropical fruits. Drink now through 2028. 1,014 cases made.",
    "taster_initials": "KM",
    "color": "White",
    "country": "United States",
    "region": "Sonoma",
    "score": 97,
    "price": 85,
    "alternate_bottle_size": "",
    "issue_date": "44408",
    "top100_year": 2021,
    "top100_rank": 11,
    "label_url": "https://mshanken-wineapi.imgix.net/Aubert/Chardonnay%20Russian%20River%20Valley%20Eastside/2019/0d069b07264bdcdaaddc7ad4b8959648",
    "wine_type": "still"
  },
  {
    "id": "1275617",
    "winery_full": "Poggio Landi",
    "wine_full": "Brunello di Montalcino",
    "vintage": "2016",
    "note": "Broad and mouthfilling, exuding floral, black cherry, blackberry, graphite and stony mineral flavors. Powerful, yet reined in by the vivid acidity, with tannins that are refined and well-integrated. Shows terrific balance and length. Best from 2025 through 2048. 6,000 cases made, 1,000 cases imported.",
    "taster_initials": "BS",
    "color": "Red",
    "country": "Italy",
    "region": "Tuscany",
    "score": 97,
    "price": 59,
    "alternate_bottle_size": "",
    "issue_date": "44377",
    "top100_year": 2021,
    "top100_rank": 12,
    "label_url": "https://mshanken-wineapi.imgix.net/Poggio%20Landi/Brunello%20di%20Montalcino/2016/5b303aa992a9ec7b41436ecb14bcd8dd",
    "wine_type": "still"
  },
  {
    "id": "1272521",
    "winery_full": "Château Carbonnieux",
    "wine_full": "Pessac-Léognan White",
    "vintage": "2018",
    "note": "A brisk lemon pith note flanks a core of lemon curd, honeysuckle, tarragon, oyster shell and salted butter notes, with a hint of warm, herbed focaccia on the finish adding range and contrast. Delicious. Sauvignon Blanc and Sémillon. Drink now through 2026. 10,835 cases made.",
    "taster_initials": "JM",
    "color": "White",
    "country": "France",
    "region": "Graves",
    "score": 94,
    "price": 44,
    "alternate_bottle_size": "",
    "issue_date": "44286",
    "top100_year": 2021,
    "top100_rank": 13,
    "label_url": "https://mshanken-wineapi.imgix.net/Ch%C3%A2teau%20Carbonnieux/Pessac-L%C3%A9ognan%20White/2018/82e6400d921f7855c9ab22fde8e054cb",
    "wine_type": "still"
  },
  {
    "id": "1269688",
    "winery_full": "Alexana",
    "wine_full": "Pinot Noir Dundee Hills Revana Vineyard",
    "vintage": "2018",
    "note": "This vibrant red is coiled with tension, offering dynamic raspberry and blueberry flavors that gather notes of spiced cinnamon and orange oil, building toward medium-grained tannins. Drink now through 2030. 1,858 cases made.",
    "taster_initials": "TF",
    "color": "Red",
    "country": "United States",
    "region": "Willamette Valley",
    "score": 94,
    "price": 55,
    "alternate_bottle_size": "",
    "issue_date": "44286",
    "top100_year": 2021,
    "top100_rank": 14,
    "label_url": "https://mshanken-wineapi.imgix.net/Alexana/Pinot%20Noir%20Dundee%20Hills%20Revana%20Vineyard/2018/bf1414aaab7bcc48961e1b415152f55e",
    "wine_type": "still"
  },
  {
    "id": "1280267",
    "winery_full": "Giuseppe Nada",
    "wine_full": "Barbaresco Casot",
    "vintage": "2017",
    "note": "A  pretty red, boasting floral, strawberry, currant and cherry aromas and flavors. Accents of hay and white pepper add depth as this cruises to the long finish. The refined structure keeps this focused and balanced. Best from 2023 through 2040. 1,166 cases made, 666 cases imported.",
    "taster_initials": "BS",
    "color": "Red",
    "country": "Italy",
    "region": "Piedmont",
    "score": 95,
    "price": 43,
    "alternate_bottle_size": "",
    "issue_date": "44515",
    "top100_year": 2021,
    "top100_rank": 15,
    "label_url": "https://mshanken-wineapi.imgix.net/Giuseppe%20Nada/Barbaresco%20Casot/2017/4b2f175c3113407d5efc6ead972d9e70",
    "wine_type": "still"
  },
  {
    "id": "1268128",
    "winery_full": "Calcareous",
    "wine_full": "Syrah Paso Robles Devil's Canyon",
    "vintage": "2018",
    "note": "Polished and multilayered, with expressive notes of fresh violet, smoky meat, raspberry and cracked pepper that build tension toward medium-grained tannins. Drink now through 2029. 845 cases made.",
    "taster_initials": "TF",
    "color": "Red",
    "country": "United States",
    "region": "Paso Robles",
    "score": 94,
    "price": 56,
    "alternate_bottle_size": "",
    "issue_date": "44316",
    "top100_year": 2021,
    "top100_rank": 16,
    "label_url": "https://mshanken-wineapi.imgix.net/Calcareous/Syrah%20Paso%20Robles%20Devil%27s%20Canyon/2018/a1527cb6b0f650648e8f5184ffae247e",
    "wine_type": "still"
  },
  {
    "id": "1276068",
    "winery_full": "Talenti",
    "wine_full": "Brunello di Montalcino",
    "vintage": "2016",
    "note": "This is supple and round, evoking macerated cherry, plum and licorice flavors, framed by accents of iron, tea and wild herbs. Solidly built, with a dense matrix of tannins enforcing the finish. Shows fine overall balance. Best from 2025 through 2045. 2,600 cases made, 660 cases imported.",
    "taster_initials": "BS",
    "color": "Red",
    "country": "Italy",
    "region": "Tuscany",
    "score": 95,
    "price": 50,
    "alternate_bottle_size": "",
    "issue_date": "44377",
    "top100_year": 2021,
    "top100_rank": 17,
    "label_url": "https://mshanken-wineapi.imgix.net/Talenti/Brunello%20di%20Montalcino/2016/f800fd04f23a403c02c87643bdb7f2ce",
    "wine_type": "still"
  },
  {
    "id": "1279035",
    "winery_full": "Burn Cottage",
    "wine_full": "Pinot Noir Central Otago Burn Cottage Vineyard",
    "vintage": "2018",
    "note": "Generous and pure, with a core of maraschino cherry, raspberry puree and red licorice flavors on a plush, velvety frame, expanding into details of sandalwood, white truffle, rosemary and cardamom. Drink now through 2036. 1,642 cases made, 500 cases imported.",
    "taster_initials": "MW",
    "color": "Red",
    "country": "New Zealand",
    "region": "Central Otago",
    "score": 95,
    "price": 65,
    "alternate_bottle_size": "",
    "issue_date": "44484",
    "top100_year": 2021,
    "top100_rank": 18,
    "label_url": "https://mshanken-wineapi.imgix.net/Burn%20Cottage/Pinot%20Noir%20Central%20Otago%20Burn%20Cottage%20Vineyard/2018/5aa2dbe9a53f3f4fcb5a9eda5605f7f5",
    "wine_type": "still"
  },
  {
    "id": "1278230",
    "winery_full": "Cayuse",
    "wine_full": "Syrah Walla Walla Valley Cailloux Vineyard",
    "vintage": "2018",
    "note": "A real knockout Syrah, structured and refined yet bubbling over with personality, offering expressive raspberry, <em>garrigue</em>, warm pebble and smoky beef tones that build tension and polish toward fine-grained tannins. Drink now through 2032. 860 cases made.",
    "taster_initials": "TF",
    "color": "Red",
    "country": "United States",
    "region": "Walla Walla Valley",
    "score": 96,
    "price": 92,
    "alternate_bottle_size": "",
    "issue_date": "44484",
    "top100_year": 2021,
    "top100_rank": 19,
    "label_url": "https://mshanken-wineapi.imgix.net/Cayuse/Syrah%20Walla%20Walla%20Valley%20Cailloux%20Vineyard/2018/e9c6a69cbe5797f54eacb42eaf2c39d0",
    "wine_type": "still"
  },
  {
    "id": "1281870",
    "winery_full": "Badia a Coltibuono",
    "wine_full": "Chianti Classico",
    "vintage": "2018",
    "note": "Though ripe and lush, this is also dense, with pointed tannins giving a physical sensation and lifting the cherry, strawberry and floral flavors. Finds a nice youthful equilibrium in the end, where mouthwatering acidity roams. Best from 2023 through 2038. 24,150 cases made, 5,295 cases imported.",
    "taster_initials": "BS",
    "color": "Red",
    "country": "Italy",
    "region": "Tuscany",
    "score": 93,
    "price": 22,
    "alternate_bottle_size": "",
    "issue_date": "44500",
    "top100_year": 2021,
    "top100_rank": 20,
    "label_url": "https://mshanken-wineapi.imgix.net/Badia%20a%20Coltibuono/Chianti%20Classico/2018/de2b7495b0de848f5a4c6591015d55b4",
    "wine_type": "still"
  },
  {
    "id": "1281427",
    "winery_full": "Luca",
    "wine_full": "Malbec Uco Valley Old Vine",
    "vintage": "2019",
    "note": "Unctuous and fine-grained flavors of dark currant and ripe cherry are supported by medium-grained tannins in this red, which is creamy midpalate, with concentrated chocolate mousse notes on the finish. Drink now through 2026. 13,000 cases made, 7,000 cases imported.",
    "taster_initials": "KM",
    "color": "Red",
    "country": "Argentina",
    "region": "Mendoza",
    "score": 93,
    "price": 35,
    "alternate_bottle_size": "",
    "issue_date": "44530",
    "top100_year": 2021,
    "top100_rank": 21,
    "label_url": "https://mshanken-wineapi.imgix.net/Luca/Malbec%20Uco%20Valley%20Old%20Vine/2019/5f4aac063622e89346d1fb9431dca53e",
    "wine_type": "still"
  },
  {
    "id": "1281780",
    "winery_full": "Arterberry Maresh",
    "wine_full": "Pinot Noir Dundee Hills Old Vines",
    "vintage": "2018",
    "note": "Structured yet elegantly layered, this version offers pretty violet, raspberry and spiced tea accents that build tension toward polished, medium-grained tannins. Drink now through 2029. 1,598 cases made.",
    "taster_initials": "TF",
    "color": "Red",
    "country": "United States",
    "region": "Willamette Valley",
    "score": 93,
    "price": 39,
    "alternate_bottle_size": "",
    "issue_date": "44476",
    "top100_year": 2021,
    "top100_rank": 22,
    "label_url": "https://mshanken-wineapi.imgix.net/Arterberry%20Maresh/Pinot%20Noir%20Dundee%20Hills%20Old%20Vines/2018/e21fc5927d9672a69f00420d6a4c5c99",
    "wine_type": "still"
  },
  {
    "id": "1276713",
    "winery_full": "John Duval",
    "wine_full": "Shiraz Barossa Entity",
    "vintage": "2019",
    "note": "Powerful, vibrant and fragrant, with dried lavender, Earl Grey, dried oregano, five-spice powder and dark chocolate aromatics to mingle with the core of velvety smooth plum, black cherry and wild blackberry flavors. The tannins firm up appealingly on the finish, which goes on and on. Drink now through 2042. 2,400 cases imported.",
    "taster_initials": "MW",
    "color": "Red",
    "country": "Australia",
    "region": "Barossa",
    "score": 94,
    "price": 40,
    "alternate_bottle_size": "",
    "issue_date": "44439",
    "top100_year": 2021,
    "top100_rank": 23,
    "label_url": "https://mshanken-wineapi.imgix.net/John%20Duval/Shiraz%20Barossa%20Entity/2019/de19b5ec5b98d98e242916d448981586",
    "wine_type": "still"
  },
  {
    "id": "1276788",
    "winery_full": "Ridge",
    "wine_full": "Geyserville Alexander Valley",
    "vintage": "2019",
    "note": "Deeply structured, yet nimble on its feet. Blackberry, fresh fennel and brown baking spices build richness and layers toward medium-grained tannins.  Zinfandel, Carignane, Petite Sirah and Alicante Bouschet. Drink now through 2030. 11,000 cases made.",
    "taster_initials": "TF",
    "color": "Red",
    "country": "United States",
    "region": "Sonoma",
    "score": 93,
    "price": 45,
    "alternate_bottle_size": "",
    "issue_date": "44377",
    "top100_year": 2021,
    "top100_rank": 24,
    "label_url": "https://mshanken-wineapi.imgix.net/Ridge/Geyserville%20Alexander%20Valley/2019/879a8bbb2752c1d5ba54a1e951898050",
    "wine_type": "still"
  },
  {
    "id": "1279386",
    "winery_full": "Wittmann",
    "wine_full": "Riesling Trocken Rheinhessen Westhofener",
    "vintage": "2019",
    "note": "Peach, quince and citrus flavors mingle in this refreshing white, with accents of spice and slate. It's balanced and the stony element builds as this cruises to a lingering aftertaste. Complex and classy. Best from 2022 through 2033. 1,250 cases made.",
    "taster_initials": "BS",
    "color": "White",
    "country": "Germany",
    "region": "Germany",
    "score": 94,
    "price": 36,
    "alternate_bottle_size": "",
    "issue_date": "44515",
    "top100_year": 2021,
    "top100_rank": 25,
    "label_url": "",
    "wine_type": "still"
  },
  {
    "id": "1278891",
    "winery_full": "Salcheto",
    "wine_full": "Vino Nobile di Montepulciano Riserva",
    "vintage": "2016",
    "note": "Boasting ripe black cherry, blackberry, floral and licorice flavors, this red is expressive and balanced. Firm tannins offer structure as this remains on the elegant side, lingering with echoes of fruit, wild herbs and mineral. Drink now through 2032. 1,250 cases made, 400 cases imported.",
    "taster_initials": "BS",
    "color": "Red",
    "country": "Italy",
    "region": "Tuscany",
    "score": 94,
    "price": 36,
    "alternate_bottle_size": "",
    "issue_date": "44469",
    "top100_year": 2021,
    "top100_rank": 26,
    "label_url": "https://mshanken-wineapi.imgix.net/Salcheto/Vino%20Nobile%20di%20Montepulciano%20Riserva/2016/6829241d3c829cbc0c02ed974d40e2d6",
    "wine_type": "still"
  },
  {
    "id": "1276843",
    "winery_full": "Evening Land",
    "wine_full": "Chardonnay Eola-Amity Hills Seven Springs",
    "vintage": "2018",
    "note": "Vibrant and steely, with layers of lime and Meyer lemon that show wet stone accents, building toward a snappy finish. Drink now through 2023. 1,145 cases made.",
    "taster_initials": "TF",
    "color": "White",
    "country": "United States",
    "region": "Willamette Valley",
    "score": 93,
    "price": 35,
    "alternate_bottle_size": "",
    "issue_date": "44469",
    "top100_year": 2021,
    "top100_rank": 27,
    "label_url": "https://mshanken-wineapi.imgix.net/Evening%20Land/Chardonnay%20Eola-Amity%20Hills%20Seven%20Springs/2018/7defb6e71e4b431fcd9eaf44a96d2c5b",
    "wine_type": "still"
  },
  {
    "id": "1278765",
    "winery_full": "Three Sticks",
    "wine_full": "Pinot Noir Sonoma Coast Price Family Estates",
    "vintage": "2019",
    "note": "Powerful and rich-tasting, with concentrated dark berry and fruit flavors that are backed by fresh acidity and tannins. Minerally midpalate, with well-knit spiciness and forest floor notes lingering on the suave finish. Best from 2022 through 2027. 554 cases made.",
    "taster_initials": "KM",
    "color": "Red",
    "country": "United States",
    "region": "Sonoma",
    "score": 95,
    "price": 65,
    "alternate_bottle_size": "",
    "issue_date": "44469",
    "top100_year": 2021,
    "top100_rank": 28,
    "label_url": "https://mshanken-wineapi.imgix.net/Three%20Sticks/Pinot%20Noir%20Sonoma%20Coast%20Price%20Family%20Estates/2019/fa634a59e4ae418030d37b3bbfc0d8c3",
    "wine_type": "still"
  },
  {
    "id": "1277049",
    "winery_full": "Sparkman",
    "wine_full": "Cabernet Sauvignon Columbia Valley Holler",
    "vintage": "2018",
    "note": "Gutsy yet polished, with deeply structured blackberry, mocha espresso and dusky spice flavors that build tension toward refined tannins. Drink now through 2029. 2,483 cases made.",
    "taster_initials": "TF",
    "color": "Red",
    "country": "United States",
    "region": "Columbia Valley",
    "score": 93,
    "price": 32,
    "alternate_bottle_size": "",
    "issue_date": "44484",
    "top100_year": 2021,
    "top100_rank": 29,
    "label_url": "https://mshanken-wineapi.imgix.net/Sparkman/Cabernet%20Sauvignon%20Columbia%20Valley%20Holler/2018/30b815a408713335e855c3c86a8809ed",
    "wine_type": "still"
  },
  {
    "id": "1275246",
    "winery_full": "Cantina del Pino",
    "wine_full": "Barbaresco",
    "vintage": "2016",
    "note": "Plump and permeated by rose, cherry, raspberry, iron, tar and tobacco flavors, this red has power and intensity. Assertive tannins emerge on the finish, yet this has plenty in reserve. Shows a fine purity and harmony. Best from 2024 through 2042. 1,050 cases made, 500 cases imported.",
    "taster_initials": "BS",
    "color": "Red",
    "country": "Italy",
    "region": "Piedmont",
    "score": 94,
    "price": 45,
    "alternate_bottle_size": "",
    "issue_date": "44316",
    "top100_year": 2021,
    "top100_rank": 30,
    "label_url": "https://mshanken-wineapi.imgix.net/Cantina%20del%20Pino/Barbaresco/2016/ff6a875478d00566ff6e8fc3d8cddfdb",
    "wine_type": "still"
  },
  {
    "id": "1275313",
    "winery_full": "Filipa Pato",
    "wine_full": "Bairrada White Nossa Calcário",
    "vintage": "2019",
    "note": "Elegantly crafted, with lemon curd, pineapple and white blossom notes. This medium-bodied white offers lovely purity and vivid minerality, with tangerine, chamomile and spice elements cascading onto the herb-tinged finish. Drink now through 2030. 1,600 cases made.",
    "taster_initials": "GS",
    "color": "White",
    "country": "Portugal",
    "region": "Portugal",
    "score": 93,
    "price": 29,
    "alternate_bottle_size": "",
    "issue_date": "44347",
    "top100_year": 2021,
    "top100_rank": 31,
    "label_url": "",
    "wine_type": "still"
  },
  {
    "id": "1281186",
    "winery_full": "Massican",
    "wine_full": "Sauvignon Blanc Napa Valley",
    "vintage": "2020",
    "note": "This vibrant white offers a sleek and mouthwatering mix of pomelo, Meyer lemon, sea salt, lime zest, dried lemongrass and pineapple flavors that are intense, seamless and memorable on the long finish. Drink now. 1,154 cases made.",
    "taster_initials": "MW",
    "color": "White",
    "country": "United States",
    "region": "Napa",
    "score": 93,
    "price": 32,
    "alternate_bottle_size": "",
    "issue_date": "44530",
    "top100_year": 2021,
    "top100_rank": 32,
    "label_url": "https://mshanken-wineapi.imgix.net/Massican/Sauvignon%20Blanc%20Napa%20Valley/2020/35989bedbcd1d5e892806ca41573b2e7",
    "wine_type": "still"
  },
  {
    "id": "1278521",
    "winery_full": "Ant Moore",
    "wine_full": "Sauvignon Blanc Marlborough Estate Series",
    "vintage": "2020",
    "note": "Vibrant, juicy and wonderfully intense, showing off fleshy notes of passion fruit, mango and citrus, with mouthwatering acidity and a touch of saline and lemongrass on the finish. Drink now. 15,000 cases made, 12,000 cases imported.",
    "taster_initials": "MW",
    "color": "White",
    "country": "New Zealand",
    "region": "Marlborough",
    "score": 92,
    "price": 17,
    "alternate_bottle_size": "",
    "issue_date": "44484",
    "top100_year": 2021,
    "top100_rank": 33,
    "label_url": "https://mshanken-wineapi.imgix.net/Ant%20Moore/Sauvignon%20Blanc%20Marlborough%20Estate%20Series/2020/602142391f11ec7d27b62a50d2d892c4",
    "wine_type": "still"
  },
  {
    "id": "1271174",
    "winery_full": "Zena Crown Vineyard",
    "wine_full": "Pinot Noir Eola-Amity Hills Slope",
    "vintage": "2017",
    "note": "Sleek and agile, yet well-structured, with graceful raspberry, mineral and spiced tea flavors that build richness and tension on the way to refined tannins. Drink now through 2028. 538 cases made.",
    "taster_initials": "TF",
    "color": "Red",
    "country": "United States",
    "region": "Willamette Valley",
    "score": 95,
    "price": 75,
    "alternate_bottle_size": "",
    "issue_date": "44255",
    "top100_year": 2021,
    "top100_rank": 34,
    "label_url": "https://mshanken-wineapi.imgix.net/Zena%20Crown%20Vineyard/Pinot%20Noir%20Eola-Amity%20Hills%20Slope/2017/e8d9fd100a3d4b339b00fe8bb2ca45c7",
    "wine_type": "still"
  },
  {
    "id": "1281023",
    "winery_full": "Château de Vaudieu",
    "wine_full": "Châteauneuf-du-Pape",
    "vintage": "2019",
    "note": "This is lovely, with lush waves of creamed plum, raspberry reduction and blackberry compote rolling through in unison, carried by a layer of black licorice while a buried minerality reverberates through the lengthy finish. Grenache, Syrah, Mourvèdre and Cinsault. Best from 2022 through 2035. 2,613 cases made, 500 cases imported.",
    "taster_initials": "JM",
    "color": "Red",
    "country": "France",
    "region": "Southern Rhône",
    "score": 94,
    "price": 49,
    "alternate_bottle_size": "",
    "issue_date": "44515",
    "top100_year": 2021,
    "top100_rank": 35,
    "label_url": "https://mshanken-wineapi.imgix.net/Ch%C3%A2teau%20de%20Vaudieu/Ch%C3%A2teauneuf-du-Pape/2019/c3cd173d530b1c25ad01b694ee444c5b",
    "wine_type": "still"
  },
  {
    "id": "1276356",
    "winery_full": "Bodegas Beronia",
    "wine_full": "Rioja Gran Reserva",
    "vintage": "2012",
    "note": "Velvety tannins give way to dark cherry, mocha and loamy earth notes,  enhanced with black tea, anise and graphite accents. Broad, but keeps focused, with solid, integrated acidity. Drink now through 2029. 5,100 cases made, 2,500 cases imported.",
    "taster_initials": "GS",
    "color": "Red",
    "country": "Spain",
    "region": "Spain",
    "score": 92,
    "price": 30,
    "alternate_bottle_size": "",
    "issue_date": "44408",
    "top100_year": 2021,
    "top100_rank": 36,
    "label_url": "",
    "wine_type": "still"
  },
  {
    "id": "1279290",
    "winery_full": "Rochioli",
    "wine_full": "Pinot Noir Russian River Valley",
    "vintage": "2019",
    "note": "Delicate and refined, this is filled with concentrated raspberry tart flavors that are laced together by plenty of cedary and underbrush accents. The fresh, juicy finish shows touches of ripe minerality and hints of white pepper. Drink now through 2027. 3,198 cases made.",
    "taster_initials": "KM",
    "color": "Red",
    "country": "United States",
    "region": "Sonoma",
    "score": 94,
    "price": 64,
    "alternate_bottle_size": "",
    "issue_date": "44469",
    "top100_year": 2021,
    "top100_rank": 37,
    "label_url": "https://mshanken-wineapi.imgix.net/Rochioli/Pinot%20Noir%20Russian%20River%20Valley/2019/b98e2254d23890afd1025b9d36ea9591",
    "wine_type": "still"
  },
  {
    "id": "1281059",
    "winery_full": "Pio Cesare",
    "wine_full": "Barbera d'Alba",
    "vintage": "2019",
    "note": "This is bright and focused, exuding blackberry, black cherry and violet flavors. Balanced and firm on the long, fruit- and earth-tinged aftertaste. Drink now through 2025. 6,000 cases made, 3,204 cases imported.",
    "taster_initials": "BS",
    "color": "Red",
    "country": "Italy",
    "region": "Piedmont",
    "score": 92,
    "price": 27,
    "alternate_bottle_size": "",
    "issue_date": "44545",
    "top100_year": 2021,
    "top100_rank": 38,
    "label_url": "https://mshanken-wineapi.imgix.net/Pio%20Cesare/Barbera%20d%27Alba/2019/b65f508165c0419a315e6528c14236d6",
    "wine_type": "still"
  },
  {
    "id": "1275491",
    "winery_full": "Vermillion",
    "wine_full": "Sierra Foothills-Sonoma County",
    "vintage": "2017",
    "note": "Plump and supple, with jammy black raspberry and pomegranate flavors that are laced with notes of licorice, smoky grilled herb and pepper. Glides on the finish toward fine-grained tannins. Grenache, Syrah, Mourvèdre, Cabernet Sauvignon and Petite Sirah. Drink now through 2027. 2,300 cases made.",
    "taster_initials": "TF",
    "color": "Red",
    "country": "United States",
    "region": "Sierra Foothills",
    "score": 92,
    "price": 35,
    "alternate_bottle_size": "",
    "issue_date": "44347",
    "top100_year": 2021,
    "top100_rank": 39,
    "label_url": "https://mshanken-wineapi.imgix.net/Vermillion/Sierra%20Foothills-Sonoma%20County/2017/5cf4e44046fac20f93170d1ced31461e",
    "wine_type": "still"
  },
  {
    "id": "1273718",
    "winery_full": "Mauro Molino",
    "wine_full": "Barolo",
    "vintage": "2016",
    "note": "This red is both spicy and earthy, with cherry and strawberry fruit between those two poles. Mint, tar and tobacco elements chime in as this remains firmly structured through the finish. Best from 2023 through 2043. 3,500 cases made, 2,200 cases imported.",
    "taster_initials": "BS",
    "color": "Red",
    "country": "Italy",
    "region": "Piedmont",
    "score": 92,
    "price": 30,
    "alternate_bottle_size": "",
    "issue_date": "44316",
    "top100_year": 2021,
    "top100_rank": 40,
    "label_url": "",
    "wine_type": "still"
  },
  {
    "id": "1273075",
    "winery_full": "Rapaura Springs",
    "wine_full": "Sauvignon Blanc Marlborough Classic",
    "vintage": "2020",
    "note": "Vibrant and intense, showing notes of lemongrass and makrut lime leaf up front, with a juicy core of passion fruit and lime flavors. The intensity gains momentum on the long finish. Drink now. 158,000 cases made, 10,000 cases imported.",
    "taster_initials": "MW",
    "color": "White",
    "country": "New Zealand",
    "region": "Marlborough",
    "score": 91,
    "price": 13,
    "alternate_bottle_size": "",
    "issue_date": "44347",
    "top100_year": 2021,
    "top100_rank": 41,
    "label_url": "https://mshanken-wineapi.imgix.net/Rapaura%20Springs/Sauvignon%20Blanc%20Marlborough%20Classic/2020/0dae5bce8c018a8807ef3d3f4c0d394a",
    "wine_type": "still"
  },
  {
    "id": "1276996",
    "winery_full": "Chateau Ste. Michelle-Dr. Loosen",
    "wine_full": "Riesling Columbia Valley Eroica",
    "vintage": "2019",
    "note": "This fresh and lovely Riesling is crisp yet supple, with notes of orange blossom, petrol and floral peach that linger on the long finish. Drink now. 12,300 cases made.",
    "taster_initials": "TF",
    "color": "White",
    "country": "United States",
    "region": "Columbia Valley",
    "score": 91,
    "price": 20,
    "alternate_bottle_size": "",
    "issue_date": "44484",
    "top100_year": 2021,
    "top100_rank": 42,
    "label_url": "https://mshanken-wineapi.imgix.net/Chateau%20Ste.%20Michelle-Dr.%20Loosen/Riesling%20Columbia%20Valley%20Eroica/2019/92ee519f0eed2c6be5c9f5c365739049",
    "wine_type": "still"
  },
  {
    "id": "1276073",
    "winery_full": "Carol Shelton",
    "wine_full": "Zinfandel Mendocino County Wild Thing Old Vine",
    "vintage": "2018",
    "note": "A juicy bomb of fruit, this red is also well-structured, with lively raspberry, toasty spice and roasted sage flavors that linger on a snappy finish. Drink now through 2028. 9,085 cases made.",
    "taster_initials": "TF",
    "color": "Red",
    "country": "United States",
    "region": "Mendocino County",
    "score": 91,
    "price": 19,
    "alternate_bottle_size": "",
    "issue_date": "44377",
    "top100_year": 2021,
    "top100_rank": 43,
    "label_url": "https://mshanken-wineapi.imgix.net/Carol%20Shelton/Zinfandel%20Mendocino%20County%20Wild%20Thing%20Old%20Vine/2018/52e869b49554fefd8abe6b5316db096c",
    "wine_type": "still"
  },
  {
    "id": "1282302",
    "winery_full": "Tenute Sella & Mosca",
    "wine_full": "Cannonau di Sardegna Riserva",
    "vintage": "2018",
    "note": "A fresh and elegant red that draws you in with an enticing nose of dried flowers and spices, layering notes of pureed raspberry, dried cherry, wild sage and citrus on the palate, with a subtle streak of salinity and light, supple tannins. Drink now through 2026. 47,000 cases made, 16,000 cases imported.",
    "taster_initials": "AN",
    "color": "Red",
    "country": "Italy",
    "region": "Sardinia",
    "score": 90,
    "price": 18,
    "alternate_bottle_size": "",
    "issue_date": "44515",
    "top100_year": 2021,
    "top100_rank": 44,
    "label_url": "https://mshanken-wineapi.imgix.net/Tenute%20Sella%20%26%20Mosca/Cannonau%20di%20Sardegna%20Riserva/2018/de42ea1edbeefd590133b7b5ced87aec",
    "wine_type": "still"
  },
  {
    "id": "1270868",
    "winery_full": "Quinta do Noval",
    "wine_full": "Vintage Port",
    "vintage": "2018",
    "note": "Juicy and muscular, with a ball of plum paste, warmed fig compote and black currant reduction flavors that need time to unwind. Ample graphite- and bramble-accented grip underscores the fruit on the finish, while a ganache note finds room to strut its stuff in the end. Should be one of the longer-lived wines of the vintage. Touriga Nacional, Touriga Franca, Tinta Cão, Sousão and Tinta Roriz. Best from 2030 through 2055. 1,600 cases made, 490 cases imported.",
    "taster_initials": "JM",
    "color": "Red",
    "country": "Portugal",
    "region": "Portugal",
    "score": 97,
    "price": 100,
    "alternate_bottle_size": "",
    "issue_date": "44255",
    "top100_year": 2021,
    "top100_rank": 45,
    "label_url": "https://mshanken-wineapi.imgix.net/Quinta%20do%20Noval/Vintage%20Port/2018/6b08187d7f85276b1b49a1f4b3066d26",
    "wine_type": "dessert"
  },
  {
    "id": "1282097",
    "winery_full": "Rocca di Montegrossi",
    "wine_full": "Chianti Classico San Marcellino Gran Selezione",
    "vintage": "2016",
    "note": "A meaty, muscular version, this red displays black cherry, blackberry, tar, leather and iron aromas and flavors, offering a beam of fruit within a tightly wound, vibrant structure. Fine length. Sangiovese and Canaiolo. Best from 2024 through 2045. 1,450 cases made, 500 cases imported.",
    "taster_initials": "BS",
    "color": "Red",
    "country": "Italy",
    "region": "Tuscany",
    "score": 95,
    "price": 75,
    "alternate_bottle_size": "",
    "issue_date": "44530",
    "top100_year": 2021,
    "top100_rank": 46,
    "label_url": "https://mshanken-wineapi.imgix.net/Rocca%20di%20Montegrossi/Chianti%20Classico%20San%20Marcellino%20Gran%20Selezione/2016/ab590184a62126fccd89209dd8ebc474",
    "wine_type": "still"
  },
  {
    "id": "1281382",
    "winery_full": "MacDonald",
    "wine_full": "Cabernet Sauvignon Oakville",
    "vintage": "2018",
    "note": "This is pumping along nicely, with a torrent of cassis and crushed plum fruit at first, followed quickly by a second wave of steeped blackberry and boysenberry flavors. Underneath there's a well-embedded singed alder note and a steady tug of warm, gravelly earth. Racy licorice snap and sassafras notes chime through the finish, adding more energy to what is already an impressively <em>terroir</em>-driven wine. Best from 2022 through 2040. 500 cases made.",
    "taster_initials": "JM",
    "color": "Red",
    "country": "United States",
    "region": "Napa",
    "score": 98,
    "price": 185,
    "alternate_bottle_size": "",
    "issue_date": "44500",
    "top100_year": 2021,
    "top100_rank": 47,
    "label_url": "https://mshanken-wineapi.imgix.net/Macdonald/Cabernet%20Sauvignon%20Oakville/2018/4d9e36184185ad00f95f075b522a68df",
    "wine_type": "still"
  },
  {
    "id": "1273353",
    "winery_full": "Domaine de Villaine",
    "wine_full": "Bouzeron",
    "vintage": "2018",
    "note": "A fresh, crystalline white, this offers lemon, green apple, almond and salty mineral flavors. Though rich, it is detailed and well-defined by vibrant acidity. Shows fine balance and length, leaving a hint of wild herbs on the finish. Drink now through 2025. 1,000 cases imported.",
    "taster_initials": "BS",
    "color": "White",
    "country": "France",
    "region": "Chalonnaise",
    "score": 92,
    "price": 42,
    "alternate_bottle_size": "",
    "issue_date": "44347",
    "top100_year": 2021,
    "top100_rank": 48,
    "label_url": "",
    "wine_type": "still"
  },
  {
    "id": "1274788",
    "winery_full": "Hickinbotham",
    "wine_full": "Shiraz McLaren Vale Brooks Road",
    "vintage": "2018",
    "note": "A rich, succulent mix of dark chocolate, spiced plum, wild blackberry and black licorice notes. Showcases both power and elegance, with chai, cigar box, violets and dried sage notes, velvety and generous, on the long, generous finish. Drink now through 2035. 1,900 cases made, 370 cases imported.",
    "taster_initials": "MW",
    "color": "Red",
    "country": "Australia",
    "region": "Other South Australia",
    "score": 95,
    "price": 75,
    "alternate_bottle_size": "",
    "issue_date": "44377",
    "top100_year": 2021,
    "top100_rank": 49,
    "label_url": "https://mshanken-wineapi.imgix.net/Hickinbotham/Shiraz%20McLaren%20Vale%20Brooks%20Road/2018/2592421c39fc86ad307142151149fbda",
    "wine_type": "still"
  },
  {
    "id": "1275989",
    "winery_full": "Schloss Gobelsburg",
    "wine_full": "Riesling Kamptal Schlosskellerei",
    "vintage": "2019",
    "note": "A mix of peach, apple and grapefruit flavors hold the middle ground in this vivid white, shaded by rosemary and crushed stone accents. Sleek and long, shows a lingering finish of citrus and mineral. Drink now through 2026. 6,000 cases made, 600 cases imported.",
    "taster_initials": "BS",
    "color": "White",
    "country": "Austria",
    "region": "Niederösterreich",
    "score": 91,
    "price": 19,
    "alternate_bottle_size": "",
    "issue_date": "44408",
    "top100_year": 2021,
    "top100_rank": 50,
    "label_url": "",
    "wine_type": "still"
  },
  {
    "id": "1274135",
    "winery_full": "Alois Lageder",
    "wine_full": "Pinot Grigio Vigneti delle Dolomiti Terra Alpina",
    "vintage": "2019",
    "note": "Lively acidity and tangy salinity drive this creamy, light-bodied white, whose flavors of pineapple, apricot and lemon thyme show a zesty orange peel edge, followed by a lingering finish. Drink now. 25,942 cases made, 19,000 cases imported.",
    "taster_initials": "AN",
    "color": "White",
    "country": "Italy",
    "region": "Trentino/Alto Adige",
    "score": 90,
    "price": 16,
    "alternate_bottle_size": "",
    "issue_date": "44377",
    "top100_year": 2021,
    "top100_rank": 51,
    "label_url": "https://mshanken-wineapi.imgix.net/Alois%20Lageder/Pinot%20Grigio%20Vigneti%20delle%20Dolomiti%20Terra%20Alpina/2019/72e0a915b97b38f0c009c61137b5112c",
    "wine_type": "still"
  },
  {
    "id": "1280672",
    "winery_full": "Snowden",
    "wine_full": "Cabernet Sauvignon Napa Valley Brothers Vineyard",
    "vintage": "2018",
    "note": "This is ripe, warm in feel and very polished, with alluring cassis, plum reduction and melted black licorice notes pouring through, while sleek alder, loam and bay leaf accents form the backdrop for a long, steady finish. Gorgeous. Best from 2022 through 2038. 673 cases made.",
    "taster_initials": "JM",
    "color": "Red",
    "country": "United States",
    "region": "Napa",
    "score": 95,
    "price": 90,
    "alternate_bottle_size": "",
    "issue_date": "44484",
    "top100_year": 2021,
    "top100_rank": 52,
    "label_url": "https://mshanken-wineapi.imgix.net/Snowden/Cabernet%20Sauvignon%20Napa%20Valley%20Brothers%20Vineyard/2018/f41d56f8e9366873d354210936a1add9",
    "wine_type": "still"
  },
  {
    "id": "1275626",
    "winery_full": "Clos de los Siete",
    "wine_full": "Uco Valley",
    "vintage": "2018",
    "note": "Dense and powerful, with plenty of loamy notes to the dark cherry and roasted plum flavors that show creamy accents. Ends with dark chocolate on the finish. Malbec, Merlot, Cabernet Sauvignon, Syrah, Petit Verdot and Cabernet Franc. Drink now through 2024. 650,000 cases made, 22,400 cases imported.",
    "taster_initials": "KM",
    "color": "Red",
    "country": "Argentina",
    "region": "Mendoza",
    "score": 90,
    "price": 20,
    "alternate_bottle_size": "",
    "issue_date": "44469",
    "top100_year": 2021,
    "top100_rank": 53,
    "label_url": "https://mshanken-wineapi.imgix.net/Clos%20de%20los%20Siete/Uco%20Valley/2018/cf77adda4ab07089f7481ee213b9fbb6",
    "wine_type": "still"
  },
  {
    "id": "1279461",
    "winery_full": "Schloss Lieser",
    "wine_full": "Riesling Kabinett Mosel Juffer",
    "vintage": "2019",
    "note": "Aromas of peach and slate draw you in, where the juicy texture and brilliant flavors of apricot and peach drizzled with lime grab your attention. This is harmonious, complex and beautifully balanced between its richness, vibrant structure and slate component. Drink now through 2036. 75 cases imported.",
    "taster_initials": "BS",
    "color": "White",
    "country": "Germany",
    "region": "Germany",
    "score": 95,
    "price": 31,
    "alternate_bottle_size": "",
    "issue_date": "44500",
    "top100_year": 2021,
    "top100_rank": 54,
    "label_url": "",
    "wine_type": "still"
  },
  {
    "id": "1280223",
    "winery_full": "Philippe Viallet",
    "wine_full": "Vin de Savoie",
    "vintage": "2020",
    "note": "Pretty, with unadorned star fruit, fennel and jasmine notes laced with a hint of lime zest on the breezy finish. Jacquère, Chasselas, Chardonnay and Altesse. Drink now through 2022. 43,000 cases made, 7,000 cases imported.",
    "taster_initials": "JM",
    "color": "White",
    "country": "France",
    "region": "Savoie",
    "score": 90,
    "price": 14,
    "alternate_bottle_size": "",
    "issue_date": "44484",
    "top100_year": 2021,
    "top100_rank": 55,
    "label_url": "",
    "wine_type": "still"
  },
  {
    "id": "1281165",
    "winery_full": "Tedeschi",
    "wine_full": "Amarone della Valpolicella Marne 180",
    "vintage": "2017",
    "note": "Richly aromatic on the nose with savory notes of cigar box, ground coffee and smoke, a fragrant thread that transitions on the palate to underscore a pure beam of crème de cassis, damson plum preserve and olive tapenade flavors. This silky red is full-bodied yet harmonious, with fine-grained tannins emerging to firm the finish. Corvina, Corvinone, Rondinella and Rossignola. Drink now through 2030. 12,500 cases made, 600 cases imported.",
    "taster_initials": "AN",
    "color": "Red",
    "country": "Italy",
    "region": "Veneto",
    "score": 93,
    "price": 60,
    "alternate_bottle_size": "",
    "issue_date": "44500",
    "top100_year": 2021,
    "top100_rank": 56,
    "label_url": "",
    "wine_type": "still"
  },
  {
    "id": "1278582",
    "winery_full": "Bodegas Pazo de Barrantes",
    "wine_full": "Albariño Rias Baixas",
    "vintage": "2019",
    "note": "This white has a smooth, luxurious texture, with lime, honey cream, white blossom and tangerine flavors that are matched with a hint of toast and ample spice elements. Mouthwatering acidity is well-integrated, with a long, lingering finish. Drink now through 2024. 11,667 cases made, 1,620 cases imported.",
    "taster_initials": "GS",
    "color": "White",
    "country": "Spain",
    "region": "Spain",
    "score": 91,
    "price": 21,
    "alternate_bottle_size": "",
    "issue_date": "44469",
    "top100_year": 2021,
    "top100_rank": 57,
    "label_url": "",
    "wine_type": "still"
  },
  {
    "id": "1279811",
    "winery_full": "Chehalem",
    "wine_full": "Chardonnay Willamette Valley Inox Unoaked",
    "vintage": "2020",
    "note": "This white bursts with aromas of peach blossom and lemon zest, taking on a lush, succulent texture toward a crisp finish. Drink now. 5,900 cases made.",
    "taster_initials": "TF",
    "color": "White",
    "country": "United States",
    "region": "Willamette Valley",
    "score": 91,
    "price": 20,
    "alternate_bottle_size": "",
    "issue_date": "44530",
    "top100_year": 2021,
    "top100_rank": 58,
    "label_url": "https://mshanken-wineapi.imgix.net/Chehalem/Chardonnay%20Willamette%20Valley%20Inox%20Unoaked/2020/10e6b0fc59f9cbb97e870e7b11bed372",
    "wine_type": "still"
  },
  {
    "id": "1281156",
    "winery_full": "Monte del Frà",
    "wine_full": "Custoza Superiore Cà del Magro",
    "vintage": "2019",
    "note": "This elegant white is lightly mouthwatering with its citrusy acidity, offering a finely meshed range of white cherry, blood orange sorbet, lemon thyme and salty mineral notes, followed by a lingering, lightly spiced finish. Garganega, Trebbiano Toscano, Cortese and Chardonnay. Drink now through 2024. 7,000 cases made, 1,500 cases imported.",
    "taster_initials": "AN",
    "color": "White",
    "country": "Italy",
    "region": "Veneto",
    "score": 90,
    "price": 22,
    "alternate_bottle_size": "",
    "issue_date": "44515",
    "top100_year": 2021,
    "top100_rank": 59,
    "label_url": "https://mshanken-wineapi.imgix.net/Monte%20del%20Fr%C3%A0/Custoza%20Superiore%20C%C3%A0%20del%20Magro/2019/f2312fd4dd10f03c4bea1a0842bbb386",
    "wine_type": "still"
  },
  {
    "id": "1279738",
    "winery_full": "Force Majeure",
    "wine_full": "Syrah Red Mountain",
    "vintage": "2018",
    "note": "Combines power with finesse and polish, offering vibrant blackberry, crushed rock and cured pepper beef accents that gather tension toward medium-grained tannins. Drink now through 2030. 500 cases made.",
    "taster_initials": "TF",
    "color": "Red",
    "country": "United States",
    "region": "Yakima Valley",
    "score": 95,
    "price": 85,
    "alternate_bottle_size": "",
    "issue_date": "44484",
    "top100_year": 2021,
    "top100_rank": 60,
    "label_url": "https://mshanken-wineapi.imgix.net/Force%20Majeure/Syrah%20Red%20Mountain/2018/cca57af87428943a6ab9afb489df9ca5",
    "wine_type": "still"
  },
  {
    "id": "1279743",
    "winery_full": "Ben Haines",
    "wine_full": "Syrah Grampians",
    "vintage": "2020",
    "note": "Exquisite, with terrific purity and generosity to the plush pureed plum, cherry and raspberry flavors at the core, but showing off details of matcha, green olive tapenade, fresh loam, baking spices and dried rose petals on a supple, almost creamy texture. Drink now through 2037. 750 cases made, 150 cases imported.",
    "taster_initials": "MW",
    "color": "Red",
    "country": "Australia",
    "region": "Victoria",
    "score": 94,
    "price": 35,
    "alternate_bottle_size": "",
    "issue_date": "44439",
    "top100_year": 2021,
    "top100_rank": 61,
    "label_url": "",
    "wine_type": "still"
  },
  {
    "id": "1276111",
    "winery_full": "Stéphane Ogier",
    "wine_full": "Côtes du Rhône Le Temps Est Venu",
    "vintage": "2019",
    "note": "Juniper, violet and pepper notes mingle out front before the core of kirsch and plum fruit arrives, turning this into a juicy ball of anise-tinged deliciousness, with an echo of <em>garrigue</em> through the finish. Drink now through 2025. 3,700 cases imported.",
    "taster_initials": "JM",
    "color": "Red",
    "country": "France",
    "region": "Southern Rhône",
    "score": 91,
    "price": 23,
    "alternate_bottle_size": "",
    "issue_date": "44439",
    "top100_year": 2021,
    "top100_rank": 62,
    "label_url": "https://mshanken-wineapi.imgix.net/St%C3%A9phane%20Ogier/C%C3%B4tes%20du%20Rh%C3%B4ne%20Le%20Temps%20Est%20Venu/2019/cff57d583bf7bdde1e4445c5ea6b5055",
    "wine_type": "still"
  },
  {
    "id": "1273623",
    "winery_full": "G.B. Burlotto",
    "wine_full": "Barolo Monvigliero",
    "vintage": "2016",
    "note": "A distinctive red, full of savory aromas of wild thyme, juniper, eucalyptus and green olive. Flavors of cherry and strawberry enter on the palate and overall this is refined and lacy. Harmonious and long, finishing with flashes of blood orange, spice and malt. Best from 2023 through 2042. 660 cases made.",
    "taster_initials": "BS",
    "color": "Red",
    "country": "Italy",
    "region": "Piedmont",
    "score": 97,
    "price": 100,
    "alternate_bottle_size": "",
    "issue_date": "44316",
    "top100_year": 2021,
    "top100_rank": 63,
    "label_url": "https://mshanken-wineapi.imgix.net/G.B.%20Burlotto/Barolo%20Monvigliero/2016/0bd74c39a0cdeac412c6ff4c4463963f",
    "wine_type": "still"
  },
  {
    "id": "1271539",
    "winery_full": "Concha y Toro",
    "wine_full": "Syrah Buin Gravas del Maipo",
    "vintage": "2018",
    "note": "Elegant and well-structured, with concentrated dark fruit and Asian spice flavors that are filled with creamy richness. The rich finish lingers with hints of chocolate truffle and dried meat that are tightly wound. Drink now through 2025. 1,500 cases made, 250 cases imported.",
    "taster_initials": "KM",
    "color": "Red",
    "country": "Chile",
    "region": "Maipo",
    "score": 94,
    "price": 70,
    "alternate_bottle_size": "",
    "issue_date": "44316",
    "top100_year": 2021,
    "top100_rank": 64,
    "label_url": "https://mshanken-wineapi.imgix.net/Concha%20y%20Toro/Syrah%20Buin%20Gravas%20del%20Maipo/2018/97e77be3511544a5fb3d84bd4ae0e281",
    "wine_type": "still"
  },
  {
    "id": "1275284",
    "winery_full": "Bodegas Ateca",
    "wine_full": "Garnacha Calatayud Atteca Armas Old Vines",
    "vintage": "2017",
    "note": "A charming red, with appealing flavors of black cherry, cocoa and currant paste backed by elegant tannins. Elements of anise, tea and spice deliver complexity on the persistent finish. Drink now through 2029. 500 cases made, 250 cases imported.",
    "taster_initials": "GS",
    "color": "Red",
    "country": "Spain",
    "region": "Spain",
    "score": 93,
    "price": 45,
    "alternate_bottle_size": "",
    "issue_date": "44377",
    "top100_year": 2021,
    "top100_rank": 65,
    "label_url": "",
    "wine_type": "still"
  },
  {
    "id": "1277058",
    "winery_full": "De Martino",
    "wine_full": "Cabernet Sauvignon Maipo Valley Legado Reserva",
    "vintage": "2019",
    "note": "This rich and refined red has decadently spiced dark cherry and plum flavors that show toasty accents. Ends with tar and mocha hints on the structured finish. Drink now through 2026. 5,500 cases made, 1,800 cases imported.",
    "taster_initials": "KM",
    "color": "Red",
    "country": "Chile",
    "region": "Maipo",
    "score": 91,
    "price": 20,
    "alternate_bottle_size": "",
    "issue_date": "44484",
    "top100_year": 2021,
    "top100_rank": 66,
    "label_url": "https://mshanken-wineapi.imgix.net/De%20Martino/Cabernet%20Sauvignon%20Maipo%20Valley%20Legado%20Reserva/2019/4b13db6ac34d8cf88b3ecf034e823117",
    "wine_type": "still"
  },
  {
    "id": "1268890",
    "winery_full": "Bastianich",
    "wine_full": "Friulano Friuli Colli Orientali Vini Orsone",
    "vintage": "2018",
    "note": "A silky, light- to medium-bodied white, with a smoky note of toasted hazelnut layered with pear tart and a lively touch of lemon curd. Balanced and lightly mouthwatering throughout, with a rich hint of lanolin on the finish. Drink now through 2025. 2,800 cases made, 1,700 cases imported.",
    "taster_initials": "AN",
    "color": "White",
    "country": "Italy",
    "region": "Friuli/Venezia-Giulia",
    "score": 90,
    "price": 18,
    "alternate_bottle_size": "",
    "issue_date": "44347",
    "top100_year": 2021,
    "top100_rank": 67,
    "label_url": "https://mshanken-wineapi.imgix.net/Bastianich/Friulano%20Friuli%20Colli%20Orientali%20Vini%20Orsone/2018/d8abca006aec614ed3ae370f093fad7b",
    "wine_type": "still"
  },
  {
    "id": "1278603",
    "winery_full": "Etxaniz Txakolina",
    "wine_full": "Getariako Txakolina Rosado Txomin Etxaniz",
    "vintage": "2020",
    "note": "A lively rosé, with a slight spritz to the cherry, sea salt and grapefruit flavors. Refreshing, with hints of wild herb and spice notes. Drink now. 3,000 cases made, 2,000 cases imported.",
    "taster_initials": "GS",
    "color": "Rosé",
    "country": "Spain",
    "region": "Spain",
    "score": 90,
    "price": 20,
    "alternate_bottle_size": "",
    "issue_date": "44439",
    "top100_year": 2021,
    "top100_rank": 68,
    "label_url": "https://mshanken-wineapi.imgix.net/Etxaniz%20Txakolina/Getariako%20Txakolina%20Rosado%20Txomin%20Etxaniz/2020/c71a0c4f349f9f53ff18869590ef6f13",
    "wine_type": "still"
  },
  {
    "id": "1273220",
    "winery_full": "Domaine du Clos du Fief",
    "wine_full": "Juliénas Tradition",
    "vintage": "2018",
    "note": "Light-bodied, but shows nice power and focus, offering a balanced mix of currant and blackberry fruit, with white pepper, graphite, smoke and dried herb elements and light, integrated tannins. Drink now through 2026. 5,000 cases made, 1,500 cases imported.",
    "taster_initials": "GS",
    "color": "Red",
    "country": "France",
    "region": "Beaujolais",
    "score": 91,
    "price": 25,
    "alternate_bottle_size": "",
    "issue_date": "44316",
    "top100_year": 2021,
    "top100_rank": 69,
    "label_url": "https://mshanken-wineapi.imgix.net/Domaine%20du%20Clos%20du%20Fief/Juli%C3%A9nas%20Tradition/2018/1fa7921b00715451528b5b9c79f551a0",
    "wine_type": "still"
  },
  {
    "id": "1279140",
    "winery_full": "Domaine Chandon",
    "wine_full": "Brut Rosé California",
    "vintage": "NV",
    "note": "A festive sparkler, vibrant and generous, with layered strawberry, fresh ginger and spice flavors that build toward the snappy finish. Drink now. 130,000 cases made.",
    "taster_initials": "TF",
    "color": "Rosé",
    "country": "United States",
    "region": "Other California",
    "score": 90,
    "price": 19,
    "alternate_bottle_size": "",
    "issue_date": "44469",
    "top100_year": 2021,
    "top100_rank": 70,
    "label_url": "https://mshanken-wineapi.imgix.net/Domaine%20Chandon/Brut%20Ros%C3%A9%20California/2021/31f597ae9ac64c7a033ba17e8082fd07",
    "wine_type": "sparkling"
  },
  {
    "id": "1269231",
    "winery_full": "Feudo Montoni",
    "wine_full": "Nero d'Avola Sicilia Lagnusa",
    "vintage": "2017",
    "note": "This elegant red is medium-bodied and well-knit, with a hint of dried oregano layered with dried raspberry, rosehip and minerally iron flavors that show loamy earth accents. Light, taut tannins trim the well-spiced finish. Drink now through 2026. 10,000 cases made, 4,450 cases imported.",
    "taster_initials": "AN",
    "color": "Red",
    "country": "Italy",
    "region": "Sicily",
    "score": 90,
    "price": 22,
    "alternate_bottle_size": "",
    "issue_date": "44286",
    "top100_year": 2021,
    "top100_rank": 71,
    "label_url": "https://mshanken-wineapi.imgix.net/Feudo%20Montoni/Nero%20d%27Avola%20Sicilia%20Lagnusa/2017/b7d93b362879a8d49159e1a96b6621c7",
    "wine_type": "still"
  },
  {
    "id": "1280653",
    "winery_full": "Rivers-Marie",
    "wine_full": "Cabernet Sauvignon St. Helena Panek Vineyard",
    "vintage": "2018",
    "note": "Shows the vivid yet restrained profile of the vintage, with a racy mix of cassis, plum and blackberry fruit flavors inlaid deftly with hints of loam, sweet tobacco and bitter sweet ganache. Stays fresh and driven through the finish, with the fruit and earth notes working in tandem. Best from 2022 through 2036. Tasted twice, with consistent notes. 550 cases made.",
    "taster_initials": "JM",
    "color": "Red",
    "country": "United States",
    "region": "Napa",
    "score": 95,
    "price": 110,
    "alternate_bottle_size": "",
    "issue_date": "44500",
    "top100_year": 2021,
    "top100_rank": 72,
    "label_url": "https://mshanken-wineapi.imgix.net/Rivers-Marie/Cabernet%20Sauvignon%20St.%20Helena%20Panek%20Vineyard/2018/23439d26dadba8da9b583268ccfb32e5",
    "wine_type": "still"
  },
  {
    "id": "1272588",
    "winery_full": "55 Malbec",
    "wine_full": "Cabernet Sauvignon Paraje Altamira Zaha Toko Vineyard",
    "vintage": "2018",
    "note": "This robust red is filled with concentrated dark plum and blackberry flavors that turn creamy and rich-tasting midpalate. Chocolate tart accents fill the lively finish, which is backed by firm acidity and tannins. Drink now through 2025. 1,000 cases made, 1,000 cases imported.",
    "taster_initials": "KM",
    "color": "Red",
    "country": "Argentina",
    "region": "Mendoza",
    "score": 91,
    "price": 25,
    "alternate_bottle_size": "",
    "issue_date": "44515",
    "top100_year": 2021,
    "top100_rank": 73,
    "label_url": "https://mshanken-wineapi.imgix.net/55%20Malbec/Cabernet%20Sauvignon%20Paraje%20Altamira%20Zaha%20Toko%20Vineyard/2018/75743ba488ceaa5f243ce0fe987bc044",
    "wine_type": "still"
  },
  {
    "id": "1279745",
    "winery_full": "Thompson Estate",
    "wine_full": "Cabernet Sauvignon Margaret River Four Chambers",
    "vintage": "2019",
    "note": "Aromatic, with dried fennel, cedar, tomato leaf and white pepper notes that add complexity, with cedar-laced cassis and stewed plum flavors at the core and polished tannins. Very harmonious on the long finish. Drink now through 2036. 3,000 cases made, 1,100 cases imported.",
    "taster_initials": "MW",
    "color": "Red",
    "country": "Australia",
    "region": "Western Australia",
    "score": 91,
    "price": 30,
    "alternate_bottle_size": "",
    "issue_date": "44439",
    "top100_year": 2021,
    "top100_rank": 74,
    "label_url": "",
    "wine_type": "still"
  },
  {
    "id": "1270952",
    "winery_full": "Salvatore Molettieri",
    "wine_full": "Taurasi Vigna Cinque Querce",
    "vintage": "2013",
    "note": "A sleek and racy red, with sculpted tannins providing fine definition for the tightly knit flavors of cherry and black raspberry, Mediterranean scrub, star anise and graphite. It's full-bodied and dense, with the flavor range slowly unfurling in the glass and on the palate. Best from 2023 through 2035. 1,000 cases made, 100 cases imported.",
    "taster_initials": "AN",
    "color": "Red",
    "country": "Italy",
    "region": "Campania",
    "score": 94,
    "price": 51,
    "alternate_bottle_size": "",
    "issue_date": "44286",
    "top100_year": 2021,
    "top100_rank": 75,
    "label_url": "https://mshanken-wineapi.imgix.net/Salvatore%20Molettieri/Taurasi%20Vigna%20Cinque%20Querce/2013/b6d2a1e9f92913a8e6b09179afdb0d0d",
    "wine_type": "still"
  },
  {
    "id": "1280292",
    "winery_full": "Louis Roederer",
    "wine_full": "Brut Champagne Collection 242",
    "vintage": "NV",
    "note": "A bright, harmonious Champagne, layering well-cut acidity and a chalky underpinning with flavors of white cherry, crunchy pineapple, green almond and beeswax. The finely detailed mousse carries hints of saffron and spring blossom on the lingering finish. Drink now through 2024. 19,537 cases imported.",
    "taster_initials": "AN",
    "color": "White",
    "country": "France",
    "region": "Champagne",
    "score": 92,
    "price": 63,
    "alternate_bottle_size": "",
    "issue_date": "44484",
    "top100_year": 2021,
    "top100_rank": 76,
    "label_url": "",
    "wine_type": "sparkling"
  },
  {
    "id": "1279914",
    "winery_full": "Marcassin",
    "wine_full": "Pinot Noir Sonoma Coast Marcassin Vineyard",
    "vintage": "2014",
    "note": "Elegant and richly spiced, with fine-grained dried cherry and berry flavors that carry hints of aged beef and hot stone. The minerally finish is long and caressing, with silky tannins and forest floor notes. Drink now through 2028. 1,200 cases made.",
    "taster_initials": "KM",
    "color": "Red",
    "country": "United States",
    "region": "Sonoma",
    "score": 95,
    "price": 150,
    "alternate_bottle_size": "",
    "issue_date": "44469",
    "top100_year": 2021,
    "top100_rank": 77,
    "label_url": "",
    "wine_type": "still"
  },
  {
    "id": "1276852",
    "winery_full": "Bodega Matarromera",
    "wine_full": "Ribera del Duero Crianza",
    "vintage": "2018",
    "note": "This complex red has polished tannins, with a beefy undertone to the glossy cherry, anise, loamy earth and spice notes that give way to vivid tea and violet details on the finish. Drink now through 2029. 50,000 cases made, 2,000 cases imported.",
    "taster_initials": "GS",
    "color": "Red",
    "country": "Spain",
    "region": "Spain",
    "score": 91,
    "price": 35,
    "alternate_bottle_size": "",
    "issue_date": "44469",
    "top100_year": 2021,
    "top100_rank": 78,
    "label_url": "",
    "wine_type": "still"
  },
  {
    "id": "1276158",
    "winery_full": "Saxon Brown",
    "wine_full": "Chardonnay Sonoma Coast Durell Vineyard",
    "vintage": "2017",
    "note": "Rich and well-structured, with luscious richness to the peach pastry and apple tart flavors that are backed by fresh acidity. Buttered toast accents fill the plush and creamy finish. Drink now through 2026. 179 cases made.",
    "taster_initials": "KM",
    "color": "White",
    "country": "United States",
    "region": "Sonoma",
    "score": 94,
    "price": 60,
    "alternate_bottle_size": "",
    "issue_date": "44408",
    "top100_year": 2021,
    "top100_rank": 79,
    "label_url": "https://mshanken-wineapi.imgix.net/Saxon%20Brown/Chardonnay%20Sonoma%20Coast%20Durell%20Vineyard/2017/77f7c0f34b70c6b4ff6643fab17704a4",
    "wine_type": "still"
  },
  {
    "id": "1276466",
    "winery_full": "Alta Vista",
    "wine_full": "Atemporal Albaneve Vineyard Uco Valley",
    "vintage": "2018",
    "note": "Juicy and well-structured, with good cut to the concentrated red plum and wild berry flavors that are filled with rich acidity. Mineral and cooking spice accents linger on the fresh finish.  Malbec, Cabernet Sauvignon and Petit Verdot. Drink now through 2024. 30,000 cases made.",
    "taster_initials": "KM",
    "color": "Red",
    "country": "Argentina",
    "region": "Mendoza",
    "score": 90,
    "price": 22,
    "alternate_bottle_size": "",
    "issue_date": "44484",
    "top100_year": 2021,
    "top100_rank": 80,
    "label_url": "",
    "wine_type": "still"
  },
  {
    "id": "1281202",
    "winery_full": "Brandlin",
    "wine_full": "Cabernet Sauvignon Mount Veeder",
    "vintage": "2018",
    "note": "Vivid and expressive, with a lovely beam of plum, anise and boysenberry notes sailing through, flanked with sweet bay leaf and violet notes and carrying through the lengthy finish. This has the grip to cellar too, but approachable now for its vivacious fruit. Drink now through 2034. 1,800 cases made.",
    "taster_initials": "JM",
    "color": "Red",
    "country": "United States",
    "region": "Napa",
    "score": 93,
    "price": 90,
    "alternate_bottle_size": "",
    "issue_date": "44500",
    "top100_year": 2021,
    "top100_rank": 81,
    "label_url": "https://mshanken-wineapi.imgix.net/Brandlin/Cabernet%20Sauvignon%20Mount%20Veeder/2018/f07b1a76194f7a5355c8f85f70942c06",
    "wine_type": "still"
  },
  {
    "id": "1276128",
    "winery_full": "Masottina",
    "wine_full": "Extra Dry Conegliano Valdobbiadene Prosecco Superiore RDO Rive di Ogliano",
    "vintage": "2019",
    "note": "A fresh Prosecco, with a fine bead, layers a lightly mouthwatering acidity with a delicate mesh of ripe pear, apple blossom, stone and pink grapefruit zest aromas and flavors. Drink now. 9,800 cases made, 4,500 cases imported.",
    "taster_initials": "AN",
    "color": "White",
    "country": "Italy",
    "region": "Northeast",
    "score": 90,
    "price": 28,
    "alternate_bottle_size": "",
    "issue_date": "44377",
    "top100_year": 2021,
    "top100_rank": 82,
    "label_url": "",
    "wine_type": "sparkling"
  },
  {
    "id": "1282629",
    "winery_full": "Graeme & Julie Bott",
    "wine_full": "St.-Joseph White",
    "vintage": "2019",
    "note": "Very fresh and direct in profile, with a racy beam of starfruit, white peach and yellow apple flavors liberally laced with honeysuckle and chamomile accents. A salted butter note underscores the finish. Roussanne and Marsanne. Drink now through 2026. 333 cases made, 50 cases imported.",
    "taster_initials": "JM",
    "color": "White",
    "country": "France",
    "region": "Northern Rhône",
    "score": 93,
    "price": 65,
    "alternate_bottle_size": "",
    "issue_date": "44530",
    "top100_year": 2021,
    "top100_rank": 83,
    "label_url": "https://mshanken-wineapi.imgix.net/Graeme%20%26%20Julie%20Bott/St.-Joseph%20White/2019/c2f9cde9cefe5309c4482173788b436e",
    "wine_type": "still"
  },
  {
    "id": "1280488",
    "winery_full": "Chalk Hill",
    "wine_full": "Chardonnay Sonoma Coast",
    "vintage": "2019",
    "note": "Well-integrated flavors of Gala apple and ripe Bosc pear are swathed with creamy richness in this broad-textured style, with cooking spice accents lingering on the mouthwatering finish. Drink now through 2024. 28,500 cases made.",
    "taster_initials": "KM",
    "color": "White",
    "country": "United States",
    "region": "Sonoma",
    "score": 91,
    "price": 26,
    "alternate_bottle_size": "",
    "issue_date": "44500",
    "top100_year": 2021,
    "top100_rank": 84,
    "label_url": "https://mshanken-wineapi.imgix.net/Chalk%20Hill/Chardonnay%20Sonoma%20Coast/2019/1929ef1289de9038b37db4e7bc35715f",
    "wine_type": "still"
  },
  {
    "id": "1274752",
    "winery_full": "Louis Jadot",
    "wine_full": "Beaune Clos des Ursules Domaine des Héritiers",
    "vintage": "2018",
    "note": "A lithe, well-defined red, exhibiting cherry, raspberry, earth and spice aromas and flavors. It's balanced and long, with the promise of more charm in 2-3 years. Best from 2024 through 2038. 350 cases imported.",
    "taster_initials": "BS",
    "color": "Red",
    "country": "France",
    "region": "Côte de Beaune",
    "score": 93,
    "price": 95,
    "alternate_bottle_size": "",
    "issue_date": "44347",
    "top100_year": 2021,
    "top100_rank": 85,
    "label_url": "",
    "wine_type": "still"
  },
  {
    "id": "1282312",
    "winery_full": "Boundary Breaks",
    "wine_full": "Riesling Finger Lakes Dry No. 239",
    "vintage": "2019",
    "note": "A bright, floral style with lots of honeysuckle and acacia notes leading the way for lemon peel and yellow apple fruit flavors, followed by a zingy finish. Drink now through 2024. 2,500 cases made.",
    "taster_initials": "JM",
    "color": "White",
    "country": "United States",
    "region": "Finger Lakes",
    "score": 90,
    "price": 20,
    "alternate_bottle_size": "",
    "issue_date": "44500",
    "top100_year": 2021,
    "top100_rank": 86,
    "label_url": "https://mshanken-wineapi.imgix.net/Boundary%20Breaks/Riesling%20Finger%20Lakes%20Dry%20No.%20239/2019/01b0baa5943d49477376e598c13f7aa5",
    "wine_type": "still"
  },
  {
    "id": "1280540",
    "winery_full": "Château Pradeaux",
    "wine_full": "Côtes de Provence Rosé",
    "vintage": "2020",
    "note": "This is a juicy, broad, orange-hued rosé, with blood orange, orange peel and rosewater flavors backed by firm, focused acidity. A lovely mineral undertone matches flavors of tea, peach and smoke on the long finish. Drink now. 960 cases imported.",
    "taster_initials": "GS",
    "color": "Rosé",
    "country": "France",
    "region": "Provence",
    "score": 91,
    "price": 24,
    "alternate_bottle_size": "",
    "issue_date": "44469",
    "top100_year": 2021,
    "top100_rank": 87,
    "label_url": "https://mshanken-wineapi.imgix.net/Ch%C3%A2teau%20Pradeaux/C%C3%B4tes%20de%20Provence%20Ros%C3%A9/2020/3fdd6c0ad96a03b05ca77ee248576aa5",
    "wine_type": "still"
  },
  {
    "id": "1278267",
    "winery_full": "Kinsman Eades",
    "wine_full": "Cabernet Sauvignon Calistoga La Voleuse du Chagrin",
    "vintage": "2018",
    "note": "Packed with a mix of red and black currant and blackberry fruit flavors that range from compote to coulis in feel, while vibrant licorice snap, roasted apple wood and violet notes fill in throughout. There's a serious loamy tug through the finish, along with a racy acidity that lends this well-built wine an air of freshness to boot. Best from 2022 through 2038. 203 cases made.",
    "taster_initials": "JM",
    "color": "Red",
    "country": "United States",
    "region": "Napa",
    "score": 96,
    "price": 195,
    "alternate_bottle_size": "",
    "issue_date": "44439",
    "top100_year": 2021,
    "top100_rank": 88,
    "label_url": "https://mshanken-wineapi.imgix.net/Kinsman%20Eades/Cabernet%20Sauvignon%20Calistoga%20La%20Voleuse%20du%20Chagrin/2018/5137532b255de0231104b43e7c3d60f6",
    "wine_type": "still"
  },
  {
    "id": "1271291",
    "winery_full": "Luis Seabra",
    "wine_full": "Douro Xisto Ilimitado",
    "vintage": "2018",
    "note": "Rose petal, strawberry and licorice notes are bright and elegant in this juicy red with vivid mineral undertones. Notes of raspberry, pomegranate, pine and white pepper dovetail on the moderately tannic finish. Drink now through 2026. 750 cases made, 650 cases imported.",
    "taster_initials": "GS",
    "color": "Red",
    "country": "Portugal",
    "region": "Portugal",
    "score": 91,
    "price": 27,
    "alternate_bottle_size": "",
    "issue_date": "44255",
    "top100_year": 2021,
    "top100_rank": 89,
    "label_url": "",
    "wine_type": "still"
  },
  {
    "id": "1270079",
    "winery_full": "Graci",
    "wine_full": "Etna",
    "vintage": "2018",
    "note": "Rich, savory mineral notes of tarry smoke and loamy earth on the nose are layered with roasted plum, dried cherry and wild sage on the palate of this chewy, medium-bodied red. Fresh, lightly spiced finish. Drink now through 2026. 2,900 cases made, 1,200 cases imported.",
    "taster_initials": "AN",
    "color": "Red",
    "country": "Italy",
    "region": "Sicily",
    "score": 91,
    "price": 33,
    "alternate_bottle_size": "",
    "issue_date": "44255",
    "top100_year": 2021,
    "top100_rank": 90,
    "label_url": "https://mshanken-wineapi.imgix.net/Graci/Etna/2018/d9548cd57b496f7e7ef2ca2f26beb452",
    "wine_type": "still"
  },
  {
    "id": "1275399",
    "winery_full": "Bodegas Emilio Moro",
    "wine_full": "Godello Bierzo El Zarzal",
    "vintage": "2018",
    "note": "This white shows finesse, offering generous layers of lychee, orange blossom, papaya and honey flavors that stay focused, with mineral, spice and herb underpinnings. A touch of vanilla lingers on the finish. Drink now through 2023. 2,800 cases made, 225 cases imported.",
    "taster_initials": "GS",
    "color": "White",
    "country": "Spain",
    "region": "Spain",
    "score": 92,
    "price": 28,
    "alternate_bottle_size": "",
    "issue_date": "44469",
    "top100_year": 2021,
    "top100_rank": 91,
    "label_url": "https://mshanken-wineapi.imgix.net/Bodegas%20Emilio%20Moro/Godello%20Bierzo%20El%20Zarzal/2018/5753a5b1d79800c1d0951c406d26bb92",
    "wine_type": "still"
  },
  {
    "id": "1277310",
    "winery_full": "De Wetshof",
    "wine_full": "Chardonnay Robertson Bon Vallon",
    "vintage": "2020",
    "note": "A racy version, with a core of ripe apple and pear fruit and pretty accents of elderflower, flint, Meyer lemon zest and blanched almond. Long and mouthwatering on the spiced finish. Drink now through 2026. 6,500 cases made, 500 cases imported.",
    "taster_initials": "AN",
    "color": "White",
    "country": "South Africa",
    "region": "Robertson",
    "score": 91,
    "price": 24,
    "alternate_bottle_size": "",
    "issue_date": "44408",
    "top100_year": 2021,
    "top100_rank": 92,
    "label_url": "",
    "wine_type": "still"
  },
  {
    "id": "1272422",
    "winery_full": "Guido Berlucchi",
    "wine_full": "Brut Rosé Franciacorta '61",
    "vintage": "NV",
    "note": "Enticing aromas and flavors of ripe strawberry and raspberry fruit are set on the fine, lively bead in this clean-cut, mouthwatering rosé, with a chalky underpinning. Lightly spiced on the lingering finish. Drink now through 2024. 25,000 cases made, 1,300 cases imported.",
    "taster_initials": "AN",
    "color": "Rosé",
    "country": "Italy",
    "region": "Lombardy",
    "score": 91,
    "price": 36,
    "alternate_bottle_size": "",
    "issue_date": "44316",
    "top100_year": 2021,
    "top100_rank": 93,
    "label_url": "",
    "wine_type": "sparkling"
  },
  {
    "id": "1273634",
    "winery_full": "Château Berliquet",
    "wine_full": "St.-Emilion",
    "vintage": "2018",
    "note": "This is delightful, with a fine chalky thread running through the middle of gently crushed plum and black cherry fruit flavors while sweet tobacco and bay accents hang in the background. Sneaky long. Merlot and Cabernet Franc. Drink now through 2032.",
    "taster_initials": "JM",
    "color": "Red",
    "country": "France",
    "region": "Right Bank",
    "score": 92,
    "price": 65,
    "alternate_bottle_size": "",
    "issue_date": "44286",
    "top100_year": 2021,
    "top100_rank": 94,
    "label_url": "",
    "wine_type": "still"
  },
  {
    "id": "1270565",
    "winery_full": "Colli di Lapio",
    "wine_full": "Fiano di Avellino",
    "vintage": "2019",
    "note": "Juicy white cherry and pomegranate fruit is accented by tangerine zest and a range of fragrant ground spice—lots of ginger, cardamom and white pepper. It's a bright and mouthwatering, light- to medium-bodied white, with a streak of underlying salinity driving the lingering finish. Drink now through 2026. 4,500 cases made, 800 cases imported.",
    "taster_initials": "AN",
    "color": "White",
    "country": "Italy",
    "region": "Campania",
    "score": 91,
    "price": 28,
    "alternate_bottle_size": "",
    "issue_date": "44286",
    "top100_year": 2021,
    "top100_rank": 95,
    "label_url": "",
    "wine_type": "still"
  },
  {
    "id": "1280661",
    "winery_full": "Detert",
    "wine_full": "Cabernet Franc Oakville",
    "vintage": "2018",
    "note": "Fresh and pure in profile, with a cassis and cherry core that drives along nicely, flanked by a tobacco edge before lingering over tobacco and warm earth hints on the finish. Best from 2022 through 2030. 250 cases made.",
    "taster_initials": "JM",
    "color": "Red",
    "country": "United States",
    "region": "Napa",
    "score": 92,
    "price": 95,
    "alternate_bottle_size": "",
    "issue_date": "44500",
    "top100_year": 2021,
    "top100_rank": 96,
    "label_url": "https://mshanken-wineapi.imgix.net/Detert/Cabernet%20Franc%20Oakville/2018/39ae998744bb8acdf10ed8f26f406402",
    "wine_type": "still"
  },
  {
    "id": "1272397",
    "winery_full": "Domaine Guiberteau",
    "wine_full": "Saumur White",
    "vintage": "2018",
    "note": "Tightly wound, with cardamom, hazelnut and thyme notes gliding around the stone fruit core. The acidity is pretty intense, but it's offset by hints of wood. Needs some time. Best from 2023 through 2031. 450 cases imported.",
    "taster_initials": "AZ",
    "color": "White",
    "country": "France",
    "region": "Loire",
    "score": 91,
    "price": 27,
    "alternate_bottle_size": "",
    "issue_date": "44316",
    "top100_year": 2021,
    "top100_rank": 97,
    "label_url": "",
    "wine_type": "still"
  },
  {
    "id": "1278382",
    "winery_full": "Faust",
    "wine_full": "Cabernet Sauvignon Coombsville The Pact",
    "vintage": "2018",
    "note": "Distinctive, with a well-defined mix of açaí berry, plum and blueberry fruit that has a cool and fresh feel, while racy graphite, dark earth, tobacco and violet accents fill in the background. Structured and energetic through the finish, with the fruit-earth interplay showing nice persistence. Best from 2021 through 2031. Tasted twice, with consistent notes. 2,200 cases made.",
    "taster_initials": "JM",
    "color": "Red",
    "country": "United States",
    "region": "Napa",
    "score": 93,
    "price": 125,
    "alternate_bottle_size": "",
    "issue_date": "44439",
    "top100_year": 2021,
    "top100_rank": 98,
    "label_url": "",
    "wine_type": "still"
  },
  {
    "id": "1282565",
    "winery_full": "Krug",
    "wine_full": "Brut Champagne",
    "vintage": "2008",
    "note": "There’s a supernova of sensation with each sip of this powerful version, starting with the vivid streak of mouthwatering acidity that drives a rich panoply of ripe black currant, mandarin orange peel and grilled nut flavors, accented by hints of candied ginger, briny oyster shell, verbena and ground cardamom. This burns bright from start to finish, yet its fine integration and lovely, raw silk–like mousse pull it all together into a seamless, vibrant package. Pinot Noir, Pinot Meunier and Chardonnay. Disgorged autumn 2019. Drink now through 2038.",
    "taster_initials": "AN",
    "color": "White",
    "country": "France",
    "region": "Champagne",
    "score": 99,
    "price": 309,
    "alternate_bottle_size": "",
    "issue_date": "44515",
    "top100_year": 2021,
    "top100_rank": 99,
    "label_url": "https://mshanken-wineapi.imgix.net/Krug/Brut%20Champagne/2008/03c8df6557e888bd0f24db894cc38918",
    "wine_type": "sparkling"
  },
  {
    "id": "1276797",
    "winery_full": "Kamen",
    "wine_full": "Cabernet Sauvignon Moon Mountain District Lava Block",
    "vintage": "2018",
    "note": "Packed with warm raspberry, blackberry and fig paste flavors, this impressive version is brimming with fruit, but keeps a restrained edge as fine-grained alder and sparkles of sage and sassafras provide a counterbalance. Well-embedded structure carries it all through the mouthwatering finish. Best from 2022 through 2034. 425 cases made.",
    "taster_initials": "JM",
    "color": "Red",
    "country": "United States",
    "region": "Sonoma",
    "score": 94,
    "price": 155,
    "alternate_bottle_size": "",
    "issue_date": "44439",
    "top100_year": 2021,
    "top100_rank": 100,
    "label_url": "https://mshanken-wineapi.imgix.net/Kamen/Cabernet%20Sauvignon%20Moon%20Mountain%20District%20Lava%20Block/2018/b018d7ed8abdbccae498df364fcde313",
    "wine_type": "still"
  }
]