[
  {
    "id": "1297502",
    "winery_full": "Argiano",
    "wine_full": "Brunello di Montalcino",
    "vintage": "2018",
    "note": "Rose, strawberry and cherry aromas and flavors are the main themes in this red, along with wild herb, mineral and cut hay accents. Racy and full of energy, with a long, saturated finish. Best from 2025 through 2042. 9,400 cases made, 3,504 cases imported.",
    "taster_initials": "BS",
    "color": "Red",
    "country": "Italy",
    "region": "Tuscany",
    "score": 95,
    "price": 90,
    "alternate_bottle_size": "",
    "issue_date": "45107",
    "top100_year": 2023,
    "top100_rank": 1,
    "label_url": "https://mshanken-wineapi.imgix.net/Argiano/Brunello%20di%20Montalcino/2018/4d717617e8ee3f80119401bfd6e0ec44",
    "wine_type": "still"
  },
  {
    "id": "1301679",
    "winery_full": "Occidental",
    "wine_full": "Pinot Noir West Sonoma Coast Freestone-Occidental",
    "vintage": "2021",
    "note": "Boasts blackberry and plum fruit enlivened by a light savory thread, while anise and iris notes add range through the sleek, tangy finish. Shows a nice underlying mineral edge, which adds subtle tension throughout. Refined. Drink now through 2030. 4,000 cases made.",
    "taster_initials": "JM",
    "color": "Red",
    "country": "United States",
    "region": "California",
    "score": 94,
    "price": 65,
    "alternate_bottle_size": "",
    "issue_date": "45245",
    "top100_year": 2023,
    "top100_rank": 2,
    "label_url": "",
    "wine_type": "still"
  },
  {
    "id": "1295034",
    "winery_full": "Château Lynch Bages",
    "wine_full": "Pauillac",
    "vintage": "2020",
    "note": "Gorgeous from the start, with cassis and violet notes leading off, followed by additional waves of black cherry and blackberry fruit as well as sweet tobacco and iron. Shows subtle savory and cedar hints that stay in the background, as the iron note pierces through the fruit on the finish. Almost approachable for the fruit, but wait if you can. Cabernet Sauvignon, Merlot, Petit Verdot and Cabernet Franc. Best from 2026 through 2040. 20,000 cases made.",
    "taster_initials": "JM",
    "color": "Red",
    "country": "France",
    "region": "Bordeaux",
    "score": 96,
    "price": 137,
    "alternate_bottle_size": "",
    "issue_date": "45016",
    "top100_year": 2023,
    "top100_rank": 3,
    "label_url": "https://mshanken-wineapi.imgix.net/Ch%C3%A2teau%20Lynch%20Bages/Pauillac/2020/16820bc678c54a04921d1eee5a164b06",
    "wine_type": "still"
  },
  {
    "id": "1298588",
    "winery_full": "RAEN",
    "wine_full": "Pinot Noir Sonoma Coast Royal St. Robert Cuvée",
    "vintage": "2021",
    "note": "Beautifully defined, with pinpoint damson plum, mulberry and blood orange notes stretched out over a frame of rooibos tea and savory accents. Mouthwatering through the lengthy, unadorned finish, which relies on tension and purity. Drink now through 2032. 2,075 cases made.",
    "taster_initials": "JM",
    "color": "Red",
    "country": "United States",
    "region": "California",
    "score": 95,
    "price": 70,
    "alternate_bottle_size": "",
    "issue_date": "45199",
    "top100_year": 2023,
    "top100_rank": 4,
    "label_url": "https://mshanken-wineapi.imgix.net/Raen/Pinot%20Noir%20Sonoma%20Coast%20Royal%20St.%20Robert%20Cuv%C3%A9e/2021/aba9d8c4398709a0e6e2446eb2eb25f5",
    "wine_type": "still"
  },
  {
    "id": "1293124",
    "winery_full": "Mastroberardino",
    "wine_full": "Taurasi Radici Riserva",
    "vintage": "2016",
    "note": "A focused and fragrant red, leading with hints of pencil shavings, violet, tobacco and citrus that accent flavors of blackberry and black cherry fruit. This is refined and supple, fresh with lively acidity, but also shows weight and concentration, with sculpted tannins emerging on the mineral- and spice-laced finish. Drink now through 2036. 1,750 cases made, 833 cases imported.",
    "taster_initials": "AN",
    "color": "Red",
    "country": "Italy",
    "region": "Campania",
    "score": 95,
    "price": 73,
    "alternate_bottle_size": "",
    "issue_date": "45046",
    "top100_year": 2023,
    "top100_rank": 5,
    "label_url": "https://mshanken-wineapi.imgix.net/Mastroberardino/Taurasi%20Radici%20Riserva/2016/dcd4f9f53e097911d43d209c83d89bdd",
    "wine_type": "still"
  },
  {
    "id": "1301067",
    "winery_full": "Dunn",
    "wine_full": "Cabernet Sauvignon Howell Mountain",
    "vintage": "2019",
    "note": "Lushly fruited, this sends waves of crushed plum, boysenberry compote and blackberry paste out from the core, with a strong undercurrent of cast iron and smoldering tobacco to boot. Grippy and dense, but with a sense of polish and a note of purity in the guise of a pretty violet echo. Best from 2025 through 2040. 3,750 cases made.",
    "taster_initials": "JM",
    "color": "Red",
    "country": "United States",
    "region": "California",
    "score": 96,
    "price": 175,
    "alternate_bottle_size": "",
    "issue_date": "45245",
    "top100_year": 2023,
    "top100_rank": 6,
    "label_url": "https://mshanken-wineapi.imgix.net/Dunn/Cabernet%20Sauvignon%20Howell%20Mountain/2019/867e5fb809bc7aa248dc7191423d7885",
    "wine_type": "still"
  },
  {
    "id": "1299243",
    "winery_full": "Antinori",
    "wine_full": "Chianti Classico Marchese Antinori Riserva",
    "vintage": "2020",
    "note": "A sleek, elegant red, with fine purity to the aromas of cherry, black currant, iron, olive and tobacco. Shows new oak on the palate, lending both spiciness and structure offset by ample fruit and texture. Ends with a balanced, complex finish. Sangiovese, Cabernet Sauvignon and Merlot. Best from 2026 through 2047. 5,000 cases imported.",
    "taster_initials": "BS",
    "color": "Red",
    "country": "Italy",
    "region": "Tuscany",
    "score": 95,
    "price": 50,
    "alternate_bottle_size": "",
    "issue_date": "45230",
    "top100_year": 2023,
    "top100_rank": 7,
    "label_url": "https://mshanken-wineapi.imgix.net/Antinori/Chianti%20Classico%20Marchese%20Antinori%20Riserva/2020/45fc764b0e9550501588f3570715a6ac",
    "wine_type": "still"
  },
  {
    "id": "1295073",
    "winery_full": "Château Pichon Baron",
    "wine_full": "Pauillac",
    "vintage": "2020",
    "note": "This has a very large-scaled yet properly proportioned core of cassis, plum and blackberry fruit flavors that are remarkably pure and focused. Buried deep within is a sleek, vibrant iron spine that drives the finish as the fruit keeps pace. Extra savory, tobacco and cedar nuances fill out all the remaining available space. A towering wine, with a buttoned-up feel. Cabernet Sauvignon and Merlot. Best from 2030 through 2045. 12,404 cases made, 550 cases imported.",
    "taster_initials": "JM",
    "color": "Red",
    "country": "France",
    "region": "Bordeaux",
    "score": 97,
    "price": 165,
    "alternate_bottle_size": "",
    "issue_date": "45016",
    "top100_year": 2023,
    "top100_rank": 8,
    "label_url": "https://mshanken-wineapi.imgix.net/Ch%C3%A2teau%20Pichon%20Baron/Pauillac/2020/72b2ddbb0f25eb2efb60abefe09e1afe",
    "wine_type": "still"
  },
  {
    "id": "1296843",
    "winery_full": "Résonance",
    "wine_full": "Pinot Noir Willamette Valley",
    "vintage": "2021",
    "note": "Precise and elegantly structured, with detailed raspberry, savory tea and crushed stone accents that gather richness and tension toward refined tannins. Drink now through 2031. 10,870 cases made.",
    "taster_initials": "TF",
    "color": "Red",
    "country": "United States",
    "region": "Oregon",
    "score": 94,
    "price": 40,
    "alternate_bottle_size": "",
    "issue_date": "45107",
    "top100_year": 2023,
    "top100_rank": 9,
    "label_url": "https://mshanken-wineapi.imgix.net/R%C3%A9sonance/Pinot%20Noir%20Willamette%20Valley/2021/00f4e75be626868300fc231233fcc5db",
    "wine_type": "still"
  },
  {
    "id": "1298480",
    "winery_full": "Greywacke",
    "wine_full": "Sauvignon Blanc Marlborough",
    "vintage": "2022",
    "note": "Distinctive, succulent and wonderfully complex, offering stone fruit flavors on a rich, smooth and mouthwateringly juicy frame, with notes of honeysuckle, honey-preserved ginger, creamy lemon curd, ripe mango and flowers. Hints of spices linger on the long, expressive finish. Drink now. 10,000 cases imported.",
    "taster_initials": "MW",
    "color": "White",
    "country": "New Zealand",
    "region": "South Island",
    "score": 95,
    "price": 23,
    "alternate_bottle_size": "",
    "issue_date": "45214",
    "top100_year": 2023,
    "top100_rank": 10,
    "label_url": "https://mshanken-wineapi.imgix.net/Greywacke/Sauvignon%20Blanc%20Marlborough/2022/bd8162e9c561d8bca0e8857ec1d09216",
    "wine_type": "still"
  },
  {
    "id": "1299403",
    "winery_full": "Castello di Bossi",
    "wine_full": "Chianti Classico Gran Selezione",
    "vintage": "2019",
    "note": "There’s purity to the cherry, strawberry, rose, mineral and herb aromas and flavors in this solidly built red, which shows excellent balance and length. The muscular finish begs for more time for the beautiful fruit to assimilate. Best from 2025 through 2042. 1,700 cases made, 800 cases imported.",
    "taster_initials": "BS",
    "color": "Red",
    "country": "Italy",
    "region": "Tuscany",
    "score": 96,
    "price": 42,
    "alternate_bottle_size": "",
    "issue_date": "45214",
    "top100_year": 2023,
    "top100_rank": 11,
    "label_url": "https://mshanken-wineapi.imgix.net/Castello%20di%20Bossi/Chianti%20Classico%20Gran%20Selezione/2019/52b9cca8a1c896c0328fc2e5da1ea8e8",
    "wine_type": "still"
  },
  {
    "id": "1294325",
    "winery_full": "Clos St.-Jean",
    "wine_full": "Châteauneuf-du-Pape Vieilles Vignes",
    "vintage": "2020",
    "note": "Leads with warm ganache and fig bread notes, followed quickly by raspberry reduction accents that take some time to unwind. Showcases plum pâte de fruit, sanguine and black licorice notes, with a flicker of Turkish coffee underscoring the finish and giving this a decidedly dark profile in the end. Grenache, Syrah, Mourvèdre, Cinsault, Vaccarèse and Muscardin. Best from 2024 through 2038. 900 cases made, 670 cases imported.",
    "taster_initials": "JM",
    "color": "Red",
    "country": "France",
    "region": "Rhône",
    "score": 95,
    "price": 65,
    "alternate_bottle_size": "",
    "issue_date": "44985",
    "top100_year": 2023,
    "top100_rank": 12,
    "label_url": "https://mshanken-wineapi.imgix.net/Clos%20St.-Jean/Ch%C3%A2teauneuf-du-Pape%20Vieilles%20Vignes/2020/24f6143130ac079bb2140a51e36c3779",
    "wine_type": "still"
  },
  {
    "id": "1302017",
    "winery_full": "Quinta de la Rosa",
    "wine_full": "Douro La Rosa Reserva",
    "vintage": "2019",
    "note": "This elegant red has a sense of restraint, with vivid acidity and taut, sculpted tannins wrapped in a swath of plush texture that carries notes of crushed black currant and pureed boysenberry, violet and wild sage, sandalwood, slate and smoke. Opens in the glass, expanding on the rich profile to reveal details of ground anise and pink peppercorn, eucalyptus, espresso and toast through the lasting finish. Best from 2025 through 2035. 4,100 cases made, 500 cases imported.",
    "taster_initials": "AN",
    "color": "Red",
    "country": "Portugal",
    "region": "Portugal",
    "score": 95,
    "price": 60,
    "alternate_bottle_size": "",
    "issue_date": "45245",
    "top100_year": 2023,
    "top100_rank": 13,
    "label_url": "https://mshanken-wineapi.imgix.net/Quinta%20de%20la%20Rosa/Douro%20La%20Rosa%20Reserva/2019/ebbed40af87ee5f0917e353ff7ed28d0",
    "wine_type": "still"
  },
  {
    "id": "1298572",
    "winery_full": "Kistler",
    "wine_full": "Chardonnay Russian River Valley Vine Hill Vineyard",
    "vintage": "2020",
    "note": "Remarkable, with incredible depth and complexity, this oozes with apple pastry and buttery notes. Lemon curd flavors are juicy and mouthwatering, with salty minerality adding a savory thread, backed by floral highlights of orange blossoms that show a hint of spices. Offers nice tension between the rich flavors and vibrant acidity, with a long, graceful finish. Drink now through 2030. 900 cases made.",
    "taster_initials": "MW",
    "color": "White",
    "country": "United States",
    "region": "California",
    "score": 97,
    "price": 95,
    "alternate_bottle_size": "",
    "issue_date": "45138",
    "top100_year": 2023,
    "top100_rank": 14,
    "label_url": "https://mshanken-wineapi.imgix.net/Kistler/Chardonnay%20Russian%20River%20Valley%20Vine%20Hill%20Vineyard/2020/6acdae6097d0dd361712fa47c779fce6",
    "wine_type": "still"
  },
  {
    "id": "1296952",
    "winery_full": "Astrolabe",
    "wine_full": "Sauvignon Blanc Marlborough",
    "vintage": "2022",
    "note": "Checking all the boxes, this stunning version is fresh and vibrant yet also complex and full of flavor, from toasted green tea and lemon thyme to mouthwatering passion fruit, yuzu and mango. Ends with hints of white pepper, lemon blossoms and sea salt on the long, expressive finish. Drink now. 9,000 cases imported.",
    "taster_initials": "MW",
    "color": "White",
    "country": "New Zealand",
    "region": "South Island",
    "score": 94,
    "price": 23,
    "alternate_bottle_size": "",
    "issue_date": "45199",
    "top100_year": 2023,
    "top100_rank": 15,
    "label_url": "https://mshanken-wineapi.imgix.net/Astrolabe/Sauvignon%20Blanc%20Marlborough/2022/2549fea129b4e4be28f670308ba40b86",
    "wine_type": "still"
  },
  {
    "id": "1301013",
    "winery_full": "Domaine Drouhin",
    "wine_full": "Pinot Noir Dundee Hills Laurène",
    "vintage": "2021",
    "note": "Rich and detailed, with a deep but graceful structure, offering rose petal, raspberry, orange peel and dusky spice flavors that build tension and polish toward fine-grained tannins. Drink now through 2032. 3,029 cases made.",
    "taster_initials": "TF",
    "color": "Red",
    "country": "United States",
    "region": "Oregon",
    "score": 95,
    "price": 75,
    "alternate_bottle_size": "",
    "issue_date": "45245",
    "top100_year": 2023,
    "top100_rank": 16,
    "label_url": "https://mshanken-wineapi.imgix.net/Domaine%20Drouhin/Pinot%20Noir%20Dundee%20Hills%20Laur%C3%A8ne/2021/7bda8585900cb30e4fb86c1da39fde90",
    "wine_type": "still"
  },
  {
    "id": "1301240",
    "winery_full": "Margerum",
    "wine_full": "M5 Santa Barbara County",
    "vintage": "2021",
    "note": "Structure meets polish in this full-bodied blend, which offers deep blackberry and raspberry flavors that interplay with licorice, smoked pepper and <em>garrigue</em> and finish with well-buffed tannins. Grenache, Syrah, Mourvèdre, Counoise and Cinsault. Drink now through 2032. 2,792 cases made.",
    "taster_initials": "TF",
    "color": "Red",
    "country": "United States",
    "region": "California",
    "score": 94,
    "price": 30,
    "alternate_bottle_size": "",
    "issue_date": "45214",
    "top100_year": 2023,
    "top100_rank": 17,
    "label_url": "https://mshanken-wineapi.imgix.net/Margerum/M5%20Santa%20Barbara%20County/2021/bb5e10624dcb50a1065c3895217fdf1a",
    "wine_type": "still"
  },
  {
    "id": "1294662",
    "winery_full": "Château Grand-Puy-Lacoste",
    "wine_full": "Pauillac",
    "vintage": "2020",
    "note": "A tightly coiled Pauillac, with a blitz of iron and savory notes wrapped around a core of cassis, damson plum and black cherry. Sleek and tightly focused, with the iron note leaving a mouthwatering echo. Plenty tight through the finish, so patience is required. Cabernet Sauvignon and Merlot. Best from 2028 through 2042. 10,000 cases made.",
    "taster_initials": "JM",
    "color": "Red",
    "country": "France",
    "region": "Bordeaux",
    "score": 96,
    "price": 78,
    "alternate_bottle_size": "",
    "issue_date": "45016",
    "top100_year": 2023,
    "top100_rank": 18,
    "label_url": "https://mshanken-wineapi.imgix.net/Ch%C3%A2teau%20Grand-Puy-Lacoste/Pauillac/2020/034fec0ba095ea6112888a63a9d26a91",
    "wine_type": "still"
  },
  {
    "id": "1300669",
    "winery_full": "Martinelli",
    "wine_full": "Pinot Noir Green Valley of Russian River Valley Bondi Home Ranch Vineyard",
    "vintage": "2021",
    "note": "Loaded, with gorgeous succulent, lush boysenberry, mulberry and açaí berry fruit seamlessly inlaid with singed apple wood, anise and fruitcake details. Gains additional beguilement from a late flash of potpourri and black tea. Drink now through 2032. 863 cases made.",
    "taster_initials": "JM",
    "color": "Red",
    "country": "United States",
    "region": "California",
    "score": 95,
    "price": 76,
    "alternate_bottle_size": "",
    "issue_date": "45199",
    "top100_year": 2023,
    "top100_rank": 19,
    "label_url": "https://mshanken-wineapi.imgix.net/Martinelli/Pinot%20Noir%20Green%20Valley%20of%20Russian%20River%20Valley%20Bondi%20Home%20Ranch%20Vineyard/2021/fdf6e40d92d9cb6e6c5e1c105996a992",
    "wine_type": "still"
  },
  {
    "id": "1295603",
    "winery_full": "Purple Hands",
    "wine_full": "Pinot Noir Willamette Valley Lone Oak Ranch",
    "vintage": "2021",
    "note": "Fragrant and gracefully multilayered, with expressive cherry and pomegranate flavors that mingle with black tea and orange peel accents. Ends with fine-grained tannins. Drink now through 2031. 2,300 cases made.",
    "taster_initials": "TF",
    "color": "Red",
    "country": "United States",
    "region": "Oregon",
    "score": 94,
    "price": 30,
    "alternate_bottle_size": "",
    "issue_date": "45107",
    "top100_year": 2023,
    "top100_rank": 20,
    "label_url": "https://mshanken-wineapi.imgix.net/Purple%20Hands/Pinot%20Noir%20Willamette%20Valley%20Lone%20Oak%20Ranch/2021/0304491a50dbe3952fd0ad2fca77a361",
    "wine_type": "still"
  },
  {
    "id": "1296642",
    "winery_full": "Babich",
    "wine_full": "Sauvignon Blanc Marlborough Black Label",
    "vintage": "2022",
    "note": "Intense and generous, with mango, orange sherbet and apricot flavors, along with notes of sweetgrass and lemon blossoms on a fleshy, juicy frame. Reveals notes of fresh ginger and a hint of jasmine on the finish. Drink now. 80,000 cases made, 13,000 cases imported.",
    "taster_initials": "MW",
    "color": "White",
    "country": "New Zealand",
    "region": "South Island",
    "score": 93,
    "price": 15,
    "alternate_bottle_size": "",
    "issue_date": "45199",
    "top100_year": 2023,
    "top100_rank": 21,
    "label_url": "https://mshanken-wineapi.imgix.net/Babich/Sauvignon%20Blanc%20Marlborough%20Black%20Label/2022/c18d828211337465cd3ff217ca91cb1a",
    "wine_type": "still"
  },
  {
    "id": "1301000",
    "winery_full": "Fattoria di Fèlsina",
    "wine_full": "Chianti Classico Berardenga Riserva",
    "vintage": "2020",
    "note": "A solidly built red introduced by aromas of mint, lavender and wild rosemary. Shows cherry, raspberry, earth, iron, sanguine and tobacco flavors allied to an almost viscous texture as this cruises to the long finish. Impressive now, yet will be better in three to five years. Best from 2026 through 2045. 5,000 cases made, 2,200 cases imported.",
    "taster_initials": "BS",
    "color": "Red",
    "country": "Italy",
    "region": "Tuscany",
    "score": 94,
    "price": 40,
    "alternate_bottle_size": "",
    "issue_date": "45230",
    "top100_year": 2023,
    "top100_rank": 22,
    "label_url": "https://mshanken-wineapi.imgix.net/Fattoria%20di%20F%C3%A8lsina/Chianti%20Classico%20Berardenga%20Riserva/2020/e386d47e60640b7c978073409b57d15e",
    "wine_type": "still"
  },
  {
    "id": "1298943",
    "winery_full": "Rivers-Marie",
    "wine_full": "Pinot Noir Sonoma Coast",
    "vintage": "2021",
    "note": "Though not shy, with a seriously endowed core of blackberry and boysenberry compote flavors, this stays bright and racy, with mouthwatering acidity stretching things out to let in black tea, sweet tobacco and dried anise notes. Reveals a late flash of savory and minerally accents on the finish, ultimately offering a nice counterpoint to the fruit. Best from 2024 through 2031. 1,200 cases made.",
    "taster_initials": "JM",
    "color": "Red",
    "country": "United States",
    "region": "California",
    "score": 94,
    "price": 35,
    "alternate_bottle_size": "",
    "issue_date": "45199",
    "top100_year": 2023,
    "top100_rank": 23,
    "label_url": "https://mshanken-wineapi.imgix.net/Rivers-Marie/Pinot%20Noir%20Sonoma%20Coast/2021/6a9ea6819472ab4a2d43ea980e8728c7",
    "wine_type": "still"
  },
  {
    "id": "1302640",
    "winery_full": "Tenuta di Arceno",
    "wine_full": "Chianti Classico Riserva",
    "vintage": "2020",
    "note": "A supple, fluid red marked by flavors of macerated cherry, raspberry and boysenberry. Well-structured, with flashes of graphite and tobacco as this builds to the long, compact finish. All the components are there, this just needs time. Sangiovese and Merlot. Best from 2025 through 2042. 6,100 cases made, 4,453 cases imported.",
    "taster_initials": "BS",
    "color": "Red",
    "country": "Italy",
    "region": "Tuscany",
    "score": 94,
    "price": 45,
    "alternate_bottle_size": "",
    "issue_date": "45230",
    "top100_year": 2023,
    "top100_rank": 24,
    "label_url": "https://mshanken-wineapi.imgix.net/Tenuta%20di%20Arceno/Chianti%20Classico%20Riserva/2020/59faeea4d151dd779393ac519a373428",
    "wine_type": "still"
  },
  {
    "id": "1294791",
    "winery_full": "Château Gruaud-Larose",
    "wine_full": "St.-Julien",
    "vintage": "2020",
    "note": "Rock-solid, with a core of dark plum, boysenberry and blackberry compote flavors held together with cedar, savory, tobacco and singed apple wood notes that add texture and energy through the finish. Built for the cellar. Cabernet Sauvignon, Merlot and Cabernet Franc. Best from 2030 through 2040. 9,250 cases made.",
    "taster_initials": "JM",
    "color": "Red",
    "country": "France",
    "region": "Bordeaux",
    "score": 95,
    "price": 89,
    "alternate_bottle_size": "",
    "issue_date": "45016",
    "top100_year": 2023,
    "top100_rank": 25,
    "label_url": "https://mshanken-wineapi.imgix.net/Ch%C3%A2teau%20Gruaud-Larose/St.-Julien/2020/5496311ddf33a70309ead729b647bc6b",
    "wine_type": "still"
  },
  {
    "id": "1300615",
    "winery_full": "G.D. Vajra",
    "wine_full": "Barolo Bricco delle Viole",
    "vintage": "2019",
    "note": "A juicy Barolo, with vibrant acidity and a fluid profile that exudes cherry, raspberry, mown hay, mineral and eucalyptus aromas and flavors. Tight yet long, with excellent potential. Best from 2027 through 2048. 1,250 cases made.",
    "taster_initials": "BS",
    "color": "Red",
    "country": "Italy",
    "region": "Piedmont",
    "score": 96,
    "price": 95,
    "alternate_bottle_size": "",
    "issue_date": "45230",
    "top100_year": 2023,
    "top100_rank": 26,
    "label_url": "https://mshanken-wineapi.imgix.net/G.D.%20Vajra/Barolo%20Bricco%20delle%20Viole/2019/078a2515b6e282758153b47c80a9a2aa",
    "wine_type": "still"
  },
  {
    "id": "1298960",
    "winery_full": "Ramey",
    "wine_full": "Chardonnay Russian River Valley",
    "vintage": "2021",
    "note": "This powerful version offers mouthwatering lemon curd, lime blossom and mandarin orange flavors that show notes of fresh-grated ginger and lemon verbena. Sea salt minerality gains momentum on the finish, where grace notes of toasted green tea, citrus zest and white pepper linger. Drink now through 2030. 7,176 cases made.",
    "taster_initials": "MW",
    "color": "White",
    "country": "United States",
    "region": "California",
    "score": 94,
    "price": 50,
    "alternate_bottle_size": "",
    "issue_date": "45138",
    "top100_year": 2023,
    "top100_rank": 27,
    "label_url": "https://mshanken-wineapi.imgix.net/Ramey/Chardonnay%20Russian%20River%20Valley/2021/c3998bc8fa2c590516fd95415b3e223b",
    "wine_type": "still"
  },
  {
    "id": "1299017",
    "winery_full": "No Girls",
    "wine_full": "Double Lucky 8 Walla Walla Valley",
    "vintage": "2019",
    "note": "Handsomely built, rich and polished, with deep raspberry and pomegranate flavors laced with smoky pepper, river stone and licorice details that build dynamism toward medium-grained tannins. Grenache, Syrah and Tempranillo. Drink now through 2033. 547 cases made.",
    "taster_initials": "TF",
    "color": "Red",
    "country": "United States",
    "region": "Washington",
    "score": 95,
    "price": 55,
    "alternate_bottle_size": "",
    "issue_date": "45230",
    "top100_year": 2023,
    "top100_rank": 28,
    "label_url": "https://mshanken-wineapi.imgix.net/No%20Girls/Double%20Lucky%208%20Walla%20Walla%20Valley/2019/6737258a9d55f20b10076c0143686321",
    "wine_type": "still"
  },
  {
    "id": "1293951",
    "winery_full": "Invivo",
    "wine_full": "Sauvignon Blanc Marlborough X, Sarah Jessica Parker",
    "vintage": "2022",
    "note": "Leaps out of the glass with vivid aromas of passion fruit, pineapple and guava, with accents of sea salt, lime zest, ginger and white pepper minerality. Shows extra verve on the finish, with details of green tea and lemongrass. Drink now. 96,000 cases made, 30,000 cases imported.",
    "taster_initials": "MW",
    "color": "White",
    "country": "New Zealand",
    "region": "South Island",
    "score": 93,
    "price": 22,
    "alternate_bottle_size": "",
    "issue_date": "45138",
    "top100_year": 2023,
    "top100_rank": 29,
    "label_url": "https://mshanken-wineapi.imgix.net/Invivo/Sauvignon%20Blanc%20Marlborough%20X%2C%20Sarah%20Jessica%20Parker/2022/2f3466658fd222e2a7f17867ffdf8121",
    "wine_type": "still"
  },
  {
    "id": "1302240",
    "winery_full": "Bodegas Terrazas de los Andes",
    "wine_full": "Malbec Mendoza Reserva",
    "vintage": "2021",
    "note": "This stands out for its expressive, elegant bouquet of citrus blossoms, guava and red currant—flavors that are equally engaging and fresh on the palate, picking up mineral details and lingering nicely around polished tannins. Drink now. 150,000 cases made, 41,667 cases imported.",
    "taster_initials": "AR",
    "color": "Red",
    "country": "Argentina",
    "region": "Mendoza",
    "score": 92,
    "price": 20,
    "alternate_bottle_size": "",
    "issue_date": "45260",
    "top100_year": 2023,
    "top100_rank": 30,
    "label_url": "https://mshanken-wineapi.imgix.net/Bodegas%20Terrazas%20de%20los%20Andes/Malbec%20Mendoza%20Reserva/2021/2a26c05ebc59b9d134e2cbaae3cac516",
    "wine_type": "still"
  },
  {
    "id": "1299178",
    "winery_full": "Joel Gott",
    "wine_full": "Sauvignon Blanc California",
    "vintage": "2022",
    "note": "Aromatic, juicy and fragrant, with Key lime pie, tangerine, lime sherbet, fresh-cut green apple and fresh-grated ginger all singing on a mouthwatering frame. Ends with a long, expressive finish. Drink now. 109,000 cases made.",
    "taster_initials": "MW",
    "color": "White",
    "country": "United States",
    "region": "California",
    "score": 91,
    "price": 12,
    "alternate_bottle_size": "",
    "issue_date": "45214",
    "top100_year": 2023,
    "top100_rank": 31,
    "label_url": "https://mshanken-wineapi.imgix.net/Joel%20Gott/Sauvignon%20Blanc%20California/2022/a6d2f94d9c39837435f9214dcd71b5ce",
    "wine_type": "still"
  },
  {
    "id": "1296866",
    "winery_full": "Bergström",
    "wine_full": "Pinot Noir Chehalem Mountains Silice",
    "vintage": "2021",
    "note": "Supple, richly textured and elegantly complex, this Pinot opens with a burst of fresh raspberry, then unfolds with notes of forest floor and brown baking spices, plus a touch of licorice as it builds tension toward refined tannins. Drink now through 2032. 1,100 cases made.",
    "taster_initials": "TF",
    "color": "Red",
    "country": "United States",
    "region": "Oregon",
    "score": 95,
    "price": 92,
    "alternate_bottle_size": "",
    "issue_date": "45107",
    "top100_year": 2023,
    "top100_rank": 32,
    "label_url": "https://mshanken-wineapi.imgix.net/Bergstr%C3%B6m/Pinot%20Noir%20Chehalem%20Mountains%20Silice/2021/2a9c18e57460acf9e58f2a16ad049b85",
    "wine_type": "still"
  },
  {
    "id": "1298003",
    "winery_full": "Domaine Carneros",
    "wine_full": "Brut Carneros",
    "vintage": "2019",
    "note": "Alluring for its sleek polish and precision, this sparkler has tiers of Asian pear, strawberry, fresh almond and ginger flavors that unfurl slowly. Drink now. 25,000 cases made.",
    "taster_initials": "TF",
    "color": "White",
    "country": "United States",
    "region": "California",
    "score": 93,
    "price": 36,
    "alternate_bottle_size": "",
    "issue_date": "45214",
    "top100_year": 2023,
    "top100_rank": 33,
    "label_url": "https://mshanken-wineapi.imgix.net/Domaine%20Carneros/Brut%20Carneros/2019/f8726e6c4c84d04fc7bd40b400f70ee0",
    "wine_type": "sparkling"
  },
  {
    "id": "1298792",
    "winery_full": "Dei",
    "wine_full": "Vino Nobile di Montepulciano",
    "vintage": "2019",
    "note": "A smooth red, with cherry, plum and spice flavors shaded by savory underbrush and wild herb accents. Shows iron and tobacco details on the long finish, with fine balance and grip overall. Prugnolo Gentile and Canaiolo. Best from 2024 through 2040. 10,000 cases made, 3,500 cases imported.",
    "taster_initials": "BS",
    "color": "Red",
    "country": "Italy",
    "region": "Tuscany",
    "score": 93,
    "price": 37,
    "alternate_bottle_size": "",
    "issue_date": "45214",
    "top100_year": 2023,
    "top100_rank": 34,
    "label_url": "",
    "wine_type": "still"
  },
  {
    "id": "1293195",
    "winery_full": "Pyros",
    "wine_full": "Malbec Pedernal Valley",
    "vintage": "2019",
    "note": "Exudes aromas that foreshadow what's to come, with a central chalky-slate presence and fresh violet and mountain herb nuances underneath. Features generous raspberry and plum flavors that are fresh and pure, buoyed by lively, chalky acidity. Ends with finesse and fine tannins. Drink now through 2030. 11,000 cases made, 3,000 cases imported.",
    "taster_initials": "AR",
    "color": "Red",
    "country": "Argentina",
    "region": "San Juan",
    "score": 93,
    "price": 27,
    "alternate_bottle_size": "",
    "issue_date": "45107",
    "top100_year": 2023,
    "top100_rank": 35,
    "label_url": "https://mshanken-wineapi.imgix.net/Pyros/Malbec%20Pedernal%20Valley/2019/9ba6272ff48a4010bdc1b74337537375",
    "wine_type": "still"
  },
  {
    "id": "1293453",
    "winery_full": "Pico Maccario",
    "wine_full": "Barbera d'Asti Lavignone",
    "vintage": "2021",
    "note": "A silky, succulent red, with pure blackberry and black cherry fruit shaded by a graphite note. On the elegant side, showing terrific harmony and finesse, with excellent structure and length. Drink now through 2027. 9,000 cases made, 5,000 cases imported.",
    "taster_initials": "BS",
    "color": "Red",
    "country": "Italy",
    "region": "Piedmont",
    "score": 92,
    "price": 20,
    "alternate_bottle_size": "",
    "issue_date": "44985",
    "top100_year": 2023,
    "top100_rank": 36,
    "label_url": "https://mshanken-wineapi.imgix.net/Pico%20Maccario/Barbera%20d%27Asti%20Lavignone/2021/7b862652998b5ea3736f8c55c5ced8aa",
    "wine_type": "still"
  },
  {
    "id": "1298997",
    "winery_full": "Diatom",
    "wine_full": "Chardonnay Santa Barbara County",
    "vintage": "2022",
    "note": "Offers grilled pineapple, white peach and lemon blossom flavors that are robust and effortless on a sleek, juicy frame, with fresh-cut green apple, tarragon and sea spray notes emerging on the mouthwatering finish. Drink now. 17,000 cases made.",
    "taster_initials": "MW",
    "color": "White",
    "country": "United States",
    "region": "California",
    "score": 92,
    "price": 23,
    "alternate_bottle_size": "",
    "issue_date": "45138",
    "top100_year": 2023,
    "top100_rank": 37,
    "label_url": "https://mshanken-wineapi.imgix.net/Diatom/Chardonnay%20Santa%20Barbara%20County/2022/d8b04a8f762a20633913aef8dfe57426",
    "wine_type": "still"
  },
  {
    "id": "1295212",
    "winery_full": "First Drop",
    "wine_full": "Shiraz Barossa Mother's Milk",
    "vintage": "2021",
    "note": "A compelling red on a juicy, fresh frame, with smooth, polished tannins and fresh pomegranate and maraschino cherry flavors at the core, showing details of milk chocolate, nutmeg and white peppercorn, plus an appealing hint of toasted herbs and fresh earth. Reveals tannins that firm up on the finish, which packs a spicy kick. Drink now through 2033. 25,000 cases made, 3,000 cases imported.",
    "taster_initials": "MW",
    "color": "Red",
    "country": "Australia",
    "region": "South Australia",
    "score": 92,
    "price": 20,
    "alternate_bottle_size": "",
    "issue_date": "45107",
    "top100_year": 2023,
    "top100_rank": 38,
    "label_url": "https://mshanken-wineapi.imgix.net/First%20Drop/Shiraz%20Barossa%20Mother%27s%20Milk/2021/737517c0c0377eab3ad9d9e627946d59",
    "wine_type": "still"
  },
  {
    "id": "1295542",
    "winery_full": "Giuseppe Cortese",
    "wine_full": "Barbaresco",
    "vintage": "2019",
    "note": "A pretty red, this boasts strawberry, cherry, raspberry and rose aromas and flavors aligned to an elegant profile. Firm and intense, with a long, detailed aftertaste of fruit, rosemary and mineral accents. Best from 2025 through 2042. 850 cases made, 500 cases imported.",
    "taster_initials": "BS",
    "color": "Red",
    "country": "Italy",
    "region": "Piedmont",
    "score": 94,
    "price": 40,
    "alternate_bottle_size": "",
    "issue_date": "45046",
    "top100_year": 2023,
    "top100_rank": 39,
    "label_url": "https://mshanken-wineapi.imgix.net/Giuseppe%20Cortese/Barbaresco/2019/ea71f1a9bb1c20bc94ca31148c36b0ab",
    "wine_type": "still"
  },
  {
    "id": "1296348",
    "winery_full": "Clos Apalta",
    "wine_full": "Le Petit Clos Apalta",
    "vintage": "2019",
    "note": "An elegant, open-textured and well-contoured blend, offering alluring balsam, cassis and dark chocolate notes that fold over onto the rich palate. Picks up crushed red currant and espresso-laced berry flavors, which have great depth and linger effortlessly around suave tannins, echoing back to the core flavors. Carmenère, Merlot, Cabernet Sauvignon and Petit Verdot. Drink now through 2035. 3,499 cases made, 350 cases imported.",
    "taster_initials": "AR",
    "color": "Red",
    "country": "Chile",
    "region": "Rapel",
    "score": 94,
    "price": 55,
    "alternate_bottle_size": "",
    "issue_date": "45077",
    "top100_year": 2023,
    "top100_rank": 40,
    "label_url": "https://mshanken-wineapi.imgix.net/Clos%20Apalta/Le%20Petit%20Clos%20Apalta/2019/9da8108702b9c474ae7d228cb40274f0",
    "wine_type": "still"
  },
  {
    "id": "1298888",
    "winery_full": "Adega Cooperativa Regional de Monção",
    "wine_full": "Vinho Verde Muralhas de Monção",
    "vintage": "2022",
    "note": "There's a flinty underpinning to this fragrant white, which shows a succulent range of ripe apricot, blood orange, white blossoms, lemon peel and pickled ginger. Sleek and linear, with a hint of saline on the finish. Alvarinho and Trajadura. Drink now. 15,500 cases made, 10,000 cases imported.",
    "taster_initials": "AN",
    "color": "White",
    "country": "Portugal",
    "region": "Portugal",
    "score": 90,
    "price": 15,
    "alternate_bottle_size": "",
    "issue_date": "45214",
    "top100_year": 2023,
    "top100_rank": 41,
    "label_url": "https://mshanken-wineapi.imgix.net/Adega%20Cooperativa%20Regional%20de%20Mon%C3%A7%C3%A3o/Vinho%20Verde%20Muralhas%20de%20Mon%C3%A7%C3%A3o/2022/06f7e83120b254474d916855bbf8b6a5",
    "wine_type": "still"
  },
  {
    "id": "1293969",
    "winery_full": "Castello di Querceto",
    "wine_full": "Chianti Classico",
    "vintage": "2020",
    "note": "This shows a darker side of Chianti Classico, with black cherry, blackberry, iron and earth aromas and flavors. Succulent and balanced, with the structure emerging on the lingering aftertaste. Drink now through 2028. 14,200 cases made, 7,500 cases imported.",
    "taster_initials": "BS",
    "color": "Red",
    "country": "Italy",
    "region": "Tuscany",
    "score": 91,
    "price": 19,
    "alternate_bottle_size": "",
    "issue_date": "44985",
    "top100_year": 2023,
    "top100_rank": 42,
    "label_url": "https://mshanken-wineapi.imgix.net/Castello%20di%20Querceto/Chianti%20Classico/2020/de7b1a06b7bdf1796a1dc1d90c6ec5be",
    "wine_type": "still"
  },
  {
    "id": "1298801",
    "winery_full": "Juvé y Camps",
    "wine_full": "Brut Nature Cava Reserva de la Familia Gran Reserva",
    "vintage": "2018",
    "note": "This is distinctive for its abundantly fragrant notes of medicinal herbs and spices, on the nose and then carried on the palate by the lively, delicate mousse. Well-knit, with vivid acidity framing flavors of macerated cherry and apricot with notes of salted almond. Macabeo, Xarel-lo and Parellada. Drink now through 2026. 208,333 cases made, 10,000 cases imported.",
    "taster_initials": "AN",
    "color": "White",
    "country": "Spain",
    "region": "Spain",
    "score": 91,
    "price": 23,
    "alternate_bottle_size": "",
    "issue_date": "45138",
    "top100_year": 2023,
    "top100_rank": 43,
    "label_url": "https://mshanken-wineapi.imgix.net/Juv%C3%A9%20y%20Camps/Brut%20Nature%20Cava%20Reserva%20de%20la%20Familia%20Gran%20Reserva/2018/4c4e8fe04e7607a7c530dac9f5688e26",
    "wine_type": "sparkling"
  },
  {
    "id": "1292806",
    "winery_full": "Miguel Torres",
    "wine_full": "Carignan Maule Valley Vigno Vignadores de Carignan",
    "vintage": "2018",
    "note": "Elegant and complex, this red bursts with notes of plumeria, picking up hints of bay leaf, red currant, raspberry and blood orange. Fresh acidity activates additional layers of chalky minerality and toasty spice, backed by mineral-tinged tannins on the finish. Drink now through 2030. 3,500 cases made, 2,000 cases imported.",
    "taster_initials": "AR",
    "color": "Red",
    "country": "Chile",
    "region": "Maule",
    "score": 92,
    "price": 21,
    "alternate_bottle_size": "",
    "issue_date": "45077",
    "top100_year": 2023,
    "top100_rank": 44,
    "label_url": "https://mshanken-wineapi.imgix.net/Miguel%20Torres/Carignan%20Maule%20Valley%20Vigno%20Vignadores%20de%20Carignan/2018/9949b2384472cfb003f7694f8fa16559",
    "wine_type": "still"
  },
  {
    "id": "1300154",
    "winery_full": "Poggerino",
    "wine_full": "Chianti Classico",
    "vintage": "2021",
    "note": "The picture of harmony, elegance and purity, this red features black cherry, blackberry, violet and mineral aromas and flavors. Starts out supple, with vibrant acidity and firm tannins emerging on the finish. Drink now through 2033. 4,500 cases made, 1,800 cases imported.",
    "taster_initials": "BS",
    "color": "Red",
    "country": "Italy",
    "region": "Tuscany",
    "score": 93,
    "price": 26,
    "alternate_bottle_size": "",
    "issue_date": "45230",
    "top100_year": 2023,
    "top100_rank": 45,
    "label_url": "https://mshanken-wineapi.imgix.net/Poggerino/Chianti%20Classico/2021/af6b2f379796581339cf2be9b045caeb",
    "wine_type": "still"
  },
  {
    "id": "1295794",
    "winery_full": "Finca Sophenia",
    "wine_full": "Malbec Gualtallary Estate Reserva",
    "vintage": "2021",
    "note": "Elegant and refined, showing pepper bush, mountain herb and river stone aromas amid a fresh cherry and berry core, which shows minerally richness and lengthens nicely around the core flavors and fine tannins. Drink now through 2030. 15,000 cases made, 3,000 cases imported.",
    "taster_initials": "AR",
    "color": "Red",
    "country": "Argentina",
    "region": "Mendoza",
    "score": 92,
    "price": 25,
    "alternate_bottle_size": "",
    "issue_date": "45107",
    "top100_year": 2023,
    "top100_rank": 46,
    "label_url": "",
    "wine_type": "still"
  },
  {
    "id": "1300661",
    "winery_full": "Ratti",
    "wine_full": "Barbera d'Asti Battaglione",
    "vintage": "2021",
    "note": "This shows depth, along with a silky texture and flavors of black cherry, blackberry, violet and dark chocolate. Suave, concentrated and long, with a touch of heat that lingers. Drink now through 2028. 6,270 cases imported.",
    "taster_initials": "BS",
    "color": "Red",
    "country": "Italy",
    "region": "Piedmont",
    "score": 91,
    "price": 25,
    "alternate_bottle_size": "",
    "issue_date": "45260",
    "top100_year": 2023,
    "top100_rank": 47,
    "label_url": "https://mshanken-wineapi.imgix.net/Renato%20Ratti/Barbera%20d%27Asti%20Battaglione/2021/484cc7875e42cb78b394e6521281a77c",
    "wine_type": "still"
  },
  {
    "id": "1300068",
    "winery_full": "Alain Jaume",
    "wine_full": "Châteauneuf-du-Pape Domaine Grand Veneur Le Miocène",
    "vintage": "2021",
    "note": "Rich and concentrated, but racy too, with blackberry and dark plum fruit revealing crushed graphite and a kick of menthol, which adds freshness. Long and svelte, with refined tannins that drive the simmering, smoky close, this complex red shows a lot of stuffing. Grenache, Syrah and Mourvèdre. Drink now through 2032. 3,700 cases made, 580 cases imported.",
    "taster_initials": "KB",
    "color": "Red",
    "country": "France",
    "region": "Rhône",
    "score": 94,
    "price": 62,
    "alternate_bottle_size": "",
    "issue_date": "45230",
    "top100_year": 2023,
    "top100_rank": 48,
    "label_url": "https://mshanken-wineapi.imgix.net/Alain%20Jaume/Ch%C3%A2teauneuf-du-Pape%20Domaine%20Grand%20Veneur%20Le%20Mioc%C3%A8ne/2021/6a0ee4aa29154e9b2f9514177007100d",
    "wine_type": "still"
  },
  {
    "id": "1301405",
    "winery_full": "Saxum",
    "wine_full": "James Berry Vineyard Paso Robles Willow Creek District",
    "vintage": "2020",
    "note": "A knockout wine as always, polished yet potently built, with dynamic blackberry and raspberry flavors laced with <em>garrigue</em>, loamy mineral, fruitcake spices and smoked meat. Builds richness toward big but polished tannins. Grenache, Mataro, Syrah, Graciano, Grenache Blanc and Counoise. Drink now through 2035. 1,440 cases made.",
    "taster_initials": "TF",
    "color": "Red",
    "country": "United States",
    "region": "California",
    "score": 96,
    "price": 132,
    "alternate_bottle_size": "",
    "issue_date": "45214",
    "top100_year": 2023,
    "top100_rank": 49,
    "label_url": "https://mshanken-wineapi.imgix.net/Saxum/James%20Berry%20Vineyard%20Paso%20Robles%20Willow%20Creek%20District/2020/998fb01abf03860e84ed03559e93564b",
    "wine_type": "still"
  },
  {
    "id": "1296630",
    "winery_full": "Alexander Valley Vineyards",
    "wine_full": "Zinfandel Alexander Valley",
    "vintage": "2019",
    "note": "This zesty red is generous with sleekly layered cherry and raspberry flavors that are laced with notes of cinnamon and pepper and finish with lively tannins. Drink now through 2029. 9,000 cases made.",
    "taster_initials": "TF",
    "color": "Red",
    "country": "United States",
    "region": "California",
    "score": 91,
    "price": 24,
    "alternate_bottle_size": "",
    "issue_date": "45169",
    "top100_year": 2023,
    "top100_rank": 50,
    "label_url": "https://mshanken-wineapi.imgix.net/Alexander%20Valley%20Vineyards/Zinfandel%20Alexander%20Valley/2019/121cc2cd71bc361133cc21cd374316a2",
    "wine_type": "still"
  },
  {
    "id": "1297216",
    "winery_full": "Mionetto",
    "wine_full": "Brut Valdobbiadene Prosecco Superiore",
    "vintage": "NV",
    "note": "There's an exotic thread of jasmine, cardamom and turmeric winding through the blood orange granita, melon, lime zest and stone notes in this bright and balanced Prosecco. Drink now. 38,000 cases made, 10,000 cases imported.",
    "taster_initials": "AN",
    "color": "White",
    "country": "Italy",
    "region": "Northeast",
    "score": 90,
    "price": 20,
    "alternate_bottle_size": "",
    "issue_date": "45107",
    "top100_year": 2023,
    "top100_rank": 51,
    "label_url": "https://mshanken-wineapi.imgix.net/Mionetto/Brut%20Valdobbiadene%20Prosecco%20Superiore/2023/75b2398bcde66854ac42b728fde8fd37",
    "wine_type": "sparkling"
  },
  {
    "id": "1294584",
    "winery_full": "Bodega Garzón",
    "wine_full": "Albariño Uruguay Reserva",
    "vintage": "2022",
    "note": "Aromas of gooseberry, finger lime and ginger lead off in this refined but refreshing white, with saline-laced grapefruit and Meyer lemon at the core, followed by a clean finish. Drink now. 9,000 cases imported.",
    "taster_initials": "AR",
    "color": "White",
    "country": "Uruguay",
    "region": "Uruguay",
    "score": 90,
    "price": 20,
    "alternate_bottle_size": "",
    "issue_date": "44985",
    "top100_year": 2023,
    "top100_rank": 52,
    "label_url": "https://mshanken-wineapi.imgix.net/Bodega%20Garz%C3%B3n/Albari%C3%B1o%20Uruguay%20Reserva/2022/65f12c705216b880958cd97311ec8944",
    "wine_type": "still"
  },
  {
    "id": "1299370",
    "winery_full": "Jorge Ordoñez & Co.",
    "wine_full": "Moscatel Sierras de Málaga Botani Old Vines",
    "vintage": "2022",
    "note": "A dry, aromatic white, with mouthwatering acidity and a chalky underpinning, this refreshing sipper shows notes of nectarine, lime blossoms, pink grapefruit granita, fresh tarragon and pickled ginger. Very appealing. Drink now through 2025. 7,500 cases made, 2,500 cases imported.",
    "taster_initials": "AN",
    "color": "White",
    "country": "Spain",
    "region": "Spain",
    "score": 91,
    "price": 22,
    "alternate_bottle_size": "",
    "issue_date": "45138",
    "top100_year": 2023,
    "top100_rank": 53,
    "label_url": "",
    "wine_type": "still"
  },
  {
    "id": "1295240",
    "winery_full": "Michele Chiarlo",
    "wine_full": "Nizza Cipressi",
    "vintage": "2019",
    "note": "This dense red is very tightly wound and racy, revealing blackberry and violet flavors that show accents of tamarind and roasted almond. Still a bit compact on the finish. Drink now through 2026. 6,000 cases made, 1,000 cases imported.",
    "taster_initials": "BS",
    "color": "Red",
    "country": "Italy",
    "region": "Piedmont",
    "score": 92,
    "price": 29,
    "alternate_bottle_size": "",
    "issue_date": "45046",
    "top100_year": 2023,
    "top100_rank": 54,
    "label_url": "https://mshanken-wineapi.imgix.net/Michele%20Chiarlo/Nizza%20Cipressi/2019/d7d3f9967f6d54dfa2601ba5832a037e",
    "wine_type": "still"
  },
  {
    "id": "1303847",
    "winery_full": "Iron Horse",
    "wine_full": "Brut Green Valley of Russian River Valley Classic Vintage",
    "vintage": "2019",
    "note": "A bubbly with richness and verve, this cuvée offers lilting apple tart, crème brûlée and lemon verbena flavors that finish with a spicy accent of fresh ginger. Drink now through 2026. 2,150 cases made.",
    "taster_initials": "TF",
    "color": "White",
    "country": "United States",
    "region": "California",
    "score": 94,
    "price": 58,
    "alternate_bottle_size": "",
    "issue_date": "45275",
    "top100_year": 2023,
    "top100_rank": 55,
    "label_url": "https://mshanken-wineapi.imgix.net/Iron%20Horse/Brut%20Green%20Valley%20of%20Russian%20River%20Valley%20Classic%20Vintage/2019/b8f2acc4484fc4226a46279849670a0e",
    "wine_type": "sparkling"
  },
  {
    "id": "1300109",
    "winery_full": "Archery Summit",
    "wine_full": "Pinot Noir Willamette Valley Vireton",
    "vintage": "2021",
    "note": "Plush and elegantly detailed, with expressive rose petal, raspberry and brown baking spice accents that glide on the long, supple finish. Drink now through 2030. 1,950 cases made.",
    "taster_initials": "TF",
    "color": "Red",
    "country": "United States",
    "region": "Oregon",
    "score": 93,
    "price": 34,
    "alternate_bottle_size": "",
    "issue_date": "45245",
    "top100_year": 2023,
    "top100_rank": 56,
    "label_url": "https://mshanken-wineapi.imgix.net/Archery%20Summit/Pinot%20Noir%20Willamette%20Valley%20Vireton/2021/7f95c0ffd84e1905f20df6403a94dedf",
    "wine_type": "still"
  },
  {
    "id": "1299865",
    "winery_full": "Quinta Couselo",
    "wine_full": "Albariño Rias Baixas Turonia",
    "vintage": "2021",
    "note": "A succulent white, with hints of petrol and brine serving as a minerally underpinning for concentrated flavors of poached apricot and yellow peach, mandarin orange peel, dried tarragon and Marcona almond. Crisp, lightly spiced finish. Drink now through 2028. 3,300 cases made, 1,015 cases imported.",
    "taster_initials": "AN",
    "color": "White",
    "country": "Spain",
    "region": "Spain",
    "score": 92,
    "price": 26,
    "alternate_bottle_size": "",
    "issue_date": "45138",
    "top100_year": 2023,
    "top100_rank": 57,
    "label_url": "https://mshanken-wineapi.imgix.net/Quinta%20Couselo/Albari%C3%B1o%20Rias%20Baixas%20Turonia/2021/d6c46fdf559a236dfdd11b773412871f",
    "wine_type": "still"
  },
  {
    "id": "1288910",
    "winery_full": "Viña Quebrada de Macul",
    "wine_full": "Cabernet Sauvignon Maipo Valley Domus Aurea",
    "vintage": "2019",
    "note": "Aromatically engaging, with eucalyptus and briny olive notes paving the way, while river mint nuances dance around a rich core of blackberry and cassis. Lengthens out nicely midpalate, with iron-tinged minerality, singed orange peel and cocoa notes arriving on the finish around thick but well-integrated tannins. Distinctive for its savory qualities, but will have fans. Drink now through 2035. 1,800 cases imported.",
    "taster_initials": "AR",
    "color": "Red",
    "country": "Chile",
    "region": "Maipo",
    "score": 94,
    "price": 75,
    "alternate_bottle_size": "",
    "issue_date": "44985",
    "top100_year": 2023,
    "top100_rank": 58,
    "label_url": "https://mshanken-wineapi.imgix.net/Vi%C3%B1a%20Quebrada%20de%20Macul/Cabernet%20Sauvignon%20Maipo%20Valley%20Domus%20Aurea/2019/06b561ca6c34010e4cb500d66e8e04ab",
    "wine_type": "still"
  },
  {
    "id": "1301702",
    "winery_full": "Cecchi",
    "wine_full": "Chianti Classico Storia di Famiglia",
    "vintage": "2021",
    "note": "Laced with black cherry, black currant and violet aromas and flavors, this red is immediately appealing for its lush fruit. Balanced, fresh and long, with iron, wild herb and tobacco details. Sangiovese and Cabernet Sauvignon. Drink now through 2028. 50,000 cases made, 10,000 cases imported.",
    "taster_initials": "BS",
    "color": "Red",
    "country": "Italy",
    "region": "Tuscany",
    "score": 91,
    "price": 26,
    "alternate_bottle_size": "",
    "issue_date": "45230",
    "top100_year": 2023,
    "top100_rank": 59,
    "label_url": "",
    "wine_type": "still"
  },
  {
    "id": "1293677",
    "winery_full": "Domaine Pinson Frères",
    "wine_full": "Chablis Charlène & Laurent Pinson",
    "vintage": "2020",
    "note": "This is really singing today, featuring peach, ripe apple, oyster shell and almond aromas and flavors. Vibrant and intense, with a lingering chalky sensation. Terrific length. Drink now. 2,000 cases made, 600 cases imported.",
    "taster_initials": "BS",
    "color": "White",
    "country": "France",
    "region": "Burgundy",
    "score": 92,
    "price": 27,
    "alternate_bottle_size": "",
    "issue_date": "44985",
    "top100_year": 2023,
    "top100_rank": 60,
    "label_url": "https://mshanken-wineapi.imgix.net/Domaine%20Pinson%20Fr%C3%A8res/Chablis/2020/7ecbca485a9c7d9cf5d552f473068fea",
    "wine_type": "still"
  },
  {
    "id": "1298535",
    "winery_full": "Frank Family",
    "wine_full": "Cabernet Sauvignon Rutherford RHF",
    "vintage": "2018",
    "note": "A broad, well-structured version, with a serious core of cassis, plum reduction and blackberry paste flavors that meld steadily with melted black licorice, alder and warm earth hints. Reveals subtle violet and black tea nuances that hang in the background, staying fine-grained through the rich finish. A big wine, with nice poise. Best from 2024 through 2038. Tasted twice, with consistent notes. 2,300 cases made.",
    "taster_initials": "JM",
    "color": "Red",
    "country": "United States",
    "region": "California",
    "score": 95,
    "price": 110,
    "alternate_bottle_size": "",
    "issue_date": "45214",
    "top100_year": 2023,
    "top100_rank": 61,
    "label_url": "https://mshanken-wineapi.imgix.net/Frank%20Family/Cabernet%20Sauvignon%20Rutherford%20RHF/2018/610b1ddc5f9f8632b42a45243aca720d",
    "wine_type": "still"
  },
  {
    "id": "1294308",
    "winery_full": "Les Vins de Vienne",
    "wine_full": "Crozes-Hermitage",
    "vintage": "2020",
    "note": "Dark and concentrated, with blackberry puree and plum paste underscored by black licorice, apple wood smoke and a spine of iron mineral. Builds in power toward the smooth finish, which reveals high notes of black tea and violet. Drink now through 2030. 2,900 cases made, 800 cases imported.",
    "taster_initials": "JM",
    "color": "Red",
    "country": "France",
    "region": "Rhône",
    "score": 93,
    "price": 36,
    "alternate_bottle_size": "",
    "issue_date": "44985",
    "top100_year": 2023,
    "top100_rank": 62,
    "label_url": "https://mshanken-wineapi.imgix.net/Les%20Vins%20de%20Vienne/Crozes-Hermitage/2020/24be00d063d8bc2e122c372b205519d4",
    "wine_type": "still"
  },
  {
    "id": "1295381",
    "winery_full": "Nino Negri",
    "wine_full": "Valtellina Superiore Inferno Ca' Guicciardi",
    "vintage": "2019",
    "note": "An elegant red, with well-integrated minerally overtones, fresh juiciness and a plush texture, plus flavors of wild strawberry, fine tobacco, iron, orange peel and a touch of red licorice. The well-spiced finish keeps drawing you back for another sip. Drink now through 2030. 1,250 cases made, 500 cases imported.",
    "taster_initials": "AN",
    "color": "Red",
    "country": "Italy",
    "region": "Lombardy",
    "score": 94,
    "price": 68,
    "alternate_bottle_size": "",
    "issue_date": "45107",
    "top100_year": 2023,
    "top100_rank": 63,
    "label_url": "https://mshanken-wineapi.imgix.net/Nino%20Negri/Valtellina%20Superiore%20Ca%27%20Guicciardi%20Inferno/2019/393105b5fd557b3de96363deade4779a",
    "wine_type": "still"
  },
  {
    "id": "1296795",
    "winery_full": "Thorne & Daughters",
    "wine_full": "Pinot Noir Cape South Coast Copper Pot",
    "vintage": "2021",
    "note": "A bright, appealing red, with wild raspberry, strawberry and cherry fruit flavors front and center. A ripe, juicy version, with fragrant details of woodsy spices, dried thyme and a streak of stony minerality echoing on the lasting finish. Drink now through 2028. 1,250 cases made, 500 cases imported.",
    "taster_initials": "AN",
    "color": "Red",
    "country": "South Africa",
    "region": "Western Cape",
    "score": 92,
    "price": 21,
    "alternate_bottle_size": "",
    "issue_date": "45077",
    "top100_year": 2023,
    "top100_rank": 64,
    "label_url": "https://mshanken-wineapi.imgix.net/Thorne%20%26%20Daughters/Pinot%20Noir%20Cape%20South%20Coast%20Copper%20Pot/2021/ea37670fa5f6dc11a2419b469d2032f0",
    "wine_type": "still"
  },
  {
    "id": "1297007",
    "winery_full": "Groth",
    "wine_full": "Sauvignon Blanc Napa Valley",
    "vintage": "2022",
    "note": "Effusive and intense, with a mouthwatering quality to the lingering notes of lemon blossoms, pomelo, fresh-cut Honeycrisp apple and candied ginger preserved in honey. Drink now. 25,000 cases made.",
    "taster_initials": "MW",
    "color": "White",
    "country": "United States",
    "region": "California",
    "score": 92,
    "price": 30,
    "alternate_bottle_size": "",
    "issue_date": "45169",
    "top100_year": 2023,
    "top100_rank": 65,
    "label_url": "https://mshanken-wineapi.imgix.net/Groth/Sauvignon%20Blanc%20Napa%20Valley/2022/1a866608bf5772fa882f9f0185aba079",
    "wine_type": "still"
  },
  {
    "id": "1296062",
    "winery_full": "DeLille",
    "wine_full": "Cabernet Sauvignon Columbia Valley Métier",
    "vintage": "2021",
    "note": "Offers good energy and refined flavors of blackberry, dusky spices and black olive that build structure toward medium-grained tannins. Drink now through 2031. 16,000 cases made.",
    "taster_initials": "TF",
    "color": "Red",
    "country": "United States",
    "region": "Washington",
    "score": 91,
    "price": 30,
    "alternate_bottle_size": "",
    "issue_date": "45245",
    "top100_year": 2023,
    "top100_rank": 66,
    "label_url": "https://mshanken-wineapi.imgix.net/DeLille/Cabernet%20Sauvignon%20Columbia%20Valley%20M%C3%A9tier/2021/ad418207843b6ac673283d9ae5d29a73",
    "wine_type": "still"
  },
  {
    "id": "1293487",
    "winery_full": "Bisci",
    "wine_full": "Verdicchio di Matelica",
    "vintage": "2021",
    "note": "Aromatic, with apple blossom and peach skin notes, this lightly zesty white reveals mouthwatering acidity, a briny streak of salinity and a pretty range of ripe Honeycrisp apple, pickled ginger and nectarine accents. Drink now through 2026. 7,226 cases made, 1,000 cases imported.",
    "taster_initials": "AN",
    "color": "White",
    "country": "Italy",
    "region": "Marche",
    "score": 91,
    "price": 24,
    "alternate_bottle_size": "",
    "issue_date": "45046",
    "top100_year": 2023,
    "top100_rank": 67,
    "label_url": "https://mshanken-wineapi.imgix.net/Bisci/Verdicchio%20di%20Matelica/2021/de7e73278835bf3e4aed2ceea5dbc538",
    "wine_type": "still"
  },
  {
    "id": "1298426",
    "winery_full": "Flowers",
    "wine_full": "Pinot Noir Sonoma Coast",
    "vintage": "2021",
    "note": "This has racy, mouthwatering acidity coursing underneath the core notes of mulberry, bitter cherry and blackberry. Shows the streamlined tang of a coulis, while offering a range of additional bramble, anise and savory tea details through the finish. Delicious. Drink now through 2029. 27,000 cases made.",
    "taster_initials": "JM",
    "color": "Red",
    "country": "United States",
    "region": "California",
    "score": 93,
    "price": 55,
    "alternate_bottle_size": "",
    "issue_date": "45199",
    "top100_year": 2023,
    "top100_rank": 68,
    "label_url": "https://mshanken-wineapi.imgix.net/Flowers/Pinot%20Noir%20Sonoma%20Coast/2021/bcba158a22087086654b7b6833b070f2",
    "wine_type": "still"
  },
  {
    "id": "1300376",
    "winery_full": "Ken Wright",
    "wine_full": "Pinot Noir Eola-Amity Hills",
    "vintage": "2021",
    "note": "Grace meets structure and tension in this Pinot, which offers deep blueberry and raspberry flavors highlighted by crushed stone, forest floor and dusky spices. Ends with fine-grained tannins. Drink now through 2032. 2,261 cases made.",
    "taster_initials": "TF",
    "color": "Red",
    "country": "United States",
    "region": "Oregon",
    "score": 93,
    "price": 38,
    "alternate_bottle_size": "",
    "issue_date": "45245",
    "top100_year": 2023,
    "top100_rank": 69,
    "label_url": "https://mshanken-wineapi.imgix.net/Ken%20Wright/Pinot%20Noir%20Eola-Amity%20Hills/2021/860406cd1d1ba58c8f2e708996bdacfa",
    "wine_type": "still"
  },
  {
    "id": "1301767",
    "winery_full": "Abbazia di Novacella",
    "wine_full": "Kerner Alto Adige Valle Isarco",
    "vintage": "2022",
    "note": "This light-on-its-feet white is dry, tangy and orangey, with blood orange granita, orange blossoms and juicy tangerine acidity accented by hints of fresh tarragon and salty mineral. Drink now. 13,750 cases made, 3,300 cases imported.",
    "taster_initials": "AN",
    "color": "White",
    "country": "Italy",
    "region": "Trentino/Alto Adige",
    "score": 90,
    "price": 22,
    "alternate_bottle_size": "",
    "issue_date": "45245",
    "top100_year": 2023,
    "top100_rank": 70,
    "label_url": "https://mshanken-wineapi.imgix.net/Abbazia%20di%20Novacella/Kerner%20Alto%20Adige%20Valle%20Isarco/2022/c6411665ee693355c2bf471a8f5040d8",
    "wine_type": "still"
  },
  {
    "id": "1294404",
    "winery_full": "Selbach-Oster",
    "wine_full": "Riesling Kabinett Mosel",
    "vintage": "2020",
    "note": "An off-dry, succulent version, with great balance between notes of warm hay, spiced apple and savory dried green herbs. Hints of nutmeg and wet stone line the concentrated finish, powered by juicy, lemony acidity. Drink now through 2026. 1,500 cases imported.",
    "taster_initials": "KB",
    "color": "White",
    "country": "Germany",
    "region": "Germany",
    "score": 90,
    "price": 23,
    "alternate_bottle_size": "",
    "issue_date": "45077",
    "top100_year": 2023,
    "top100_rank": 71,
    "label_url": "https://mshanken-wineapi.imgix.net/Selbach-Oster/Riesling%20Kabinett%20Mosel/2020/920bb26477e2d49a3320f527fee67789",
    "wine_type": "still"
  },
  {
    "id": "1297591",
    "winery_full": "Poggio San Polo",
    "wine_full": "Rosso di Montalcino",
    "vintage": "2020",
    "note": "This lithe, elegant red is signaled by a burst of raspberry aromas and flavors. Shows iron and earth details as this firms up, before stretching out on the lingering finish. Drink now through 2027. 7,494 cases imported.",
    "taster_initials": "BS",
    "color": "Red",
    "country": "Italy",
    "region": "Tuscany",
    "score": 90,
    "price": 25,
    "alternate_bottle_size": "",
    "issue_date": "45199",
    "top100_year": 2023,
    "top100_rank": 72,
    "label_url": "https://mshanken-wineapi.imgix.net/Poggio%20San%20Polo/Rosso%20di%20Montalcino/2020/7d5fdc06aaa121c82e2c32f762671667",
    "wine_type": "still"
  },
  {
    "id": "1302999",
    "winery_full": "El Enemigo",
    "wine_full": "Cabernet Franc Agrelo Gran Single Vineyard",
    "vintage": "2019",
    "note": "Elegant enough to drink now, but with structure allowing for age, this version offers dusty rose petal and fresh peppercorn notes, plus a juicy core of strawberry and raspberry, with a pleasant wave of fresh acidity chiming in and carrying the flavors. Reveals subtle chocolate and gravel notes around polished tannins, with a lingering juicy berry finish. Drink now through 2035. 2,000 cases made, 1,500 cases imported.",
    "taster_initials": "AR",
    "color": "Red",
    "country": "Argentina",
    "region": "Mendoza",
    "score": 94,
    "price": 100,
    "alternate_bottle_size": "",
    "issue_date": "45260",
    "top100_year": 2023,
    "top100_rank": 73,
    "label_url": "https://mshanken-wineapi.imgix.net/El%20Enemigo/Cabernet%20Franc%20Agrelo%20Gran%20Single%20Vineyard/2019/870785e0bc8d20599a65a43b3319b9ec",
    "wine_type": "still"
  },
  {
    "id": "1299511",
    "winery_full": "Clos Berenguer",
    "wine_full": "Priorat Clos de Tafall",
    "vintage": "2020",
    "note": "A minerally red, with smoke, stone and iron on the nose, transitioning to underscore generous flavors of strawberry preserves, red licorice, violet and a savory boost of cured tobacco. Bright and juicy, but with a core of well-knit, chalky tannins that provide weight and focus. Drink now through 2030. 3,000 cases made, 2,000 cases imported.",
    "taster_initials": "AN",
    "color": "Red",
    "country": "Spain",
    "region": "Spain",
    "score": 92,
    "price": 30,
    "alternate_bottle_size": "",
    "issue_date": "45138",
    "top100_year": 2023,
    "top100_rank": 74,
    "label_url": "https://mshanken-wineapi.imgix.net/Clos%20Berenguer/Priorat%20Clos%20de%20Tafall/2020/a7ae8c13851e761de7be8290062be5df",
    "wine_type": "still"
  },
  {
    "id": "1293559",
    "winery_full": "Catabbo",
    "wine_full": "Tintilia del Molise Colle Cervino",
    "vintage": "2019",
    "note": "A bright and juicy red pierced with an aromatic thread of wild herbs and milled pepper, plus flavors of crushed black raspberry, plum sauce and tar-tinged mineral structured by light, taut tannins. Drink now through 2028. 29,336 cases made, 3,200 cases imported.",
    "taster_initials": "AN",
    "color": "Red",
    "country": "Italy",
    "region": "Molise",
    "score": 91,
    "price": 30,
    "alternate_bottle_size": "",
    "issue_date": "45046",
    "top100_year": 2023,
    "top100_rank": 75,
    "label_url": "https://mshanken-wineapi.imgix.net/Catabbo/Tintilia%20del%20Molise%20Colle%20Cervino/2019/6ac3a3820ad99f0f7976737172cdb9f0",
    "wine_type": "still"
  },
  {
    "id": "1299224",
    "winery_full": "Taylor Fladgate",
    "wine_full": "Tawny Port 20 Year Old",
    "vintage": "NV",
    "note": "Lovely, with a mix of persimmon, white peach, hazelnut, green tea and singed alder notes all moving together in streamlined harmony. The long, elegant finish has nice latent energy. Drink now. 8,000 cases imported.",
    "taster_initials": "JM",
    "color": "Red",
    "country": "Portugal",
    "region": "Portugal",
    "score": 93,
    "price": 61,
    "alternate_bottle_size": "",
    "issue_date": "45214",
    "top100_year": 2023,
    "top100_rank": 76,
    "label_url": "https://mshanken-wineapi.imgix.net/Taylor%20Fladgate/Tawny%20Port%2020%20Year%20Old/2023/d6145da2921372f0374a7448e2622d5c",
    "wine_type": "dessert"
  },
  {
    "id": "1298931",
    "winery_full": "El Coto de Rioja",
    "wine_full": "Rioja Coto de Imaz Gran Reserva",
    "vintage": "2016",
    "note": "Well-balanced and fresh, this medium-bodied version is tightly meshed at first, though opening nicely in the glass to display flavors of ripe cherry and red currant, mocha, iron and spiced orange peel. The lively finish is firmed by fine, taut tannins. Tempranillo and Graciano. Drink now through 2030. 20,000 cases made, 3,000 cases imported.",
    "taster_initials": "AN",
    "color": "Red",
    "country": "Spain",
    "region": "Spain",
    "score": 92,
    "price": 35,
    "alternate_bottle_size": "",
    "issue_date": "45138",
    "top100_year": 2023,
    "top100_rank": 77,
    "label_url": "",
    "wine_type": "still"
  },
  {
    "id": "1300547",
    "winery_full": "Paolo Scavino",
    "wine_full": "Barolo",
    "vintage": "2019",
    "note": "A supple, vibrant Barolo, with fine depth to the cherry, raspberry and floral aromas and flavors. Solidly built, with refined tannins and a long, juicy aftertaste. Reveals earth, iron and tobacco accents that linger. Best from 2026 through 2042. 3,000 cases made, 900 cases imported.",
    "taster_initials": "BS",
    "color": "Red",
    "country": "Italy",
    "region": "Piedmont",
    "score": 93,
    "price": 63,
    "alternate_bottle_size": "",
    "issue_date": "45260",
    "top100_year": 2023,
    "top100_rank": 78,
    "label_url": "https://mshanken-wineapi.imgix.net/Paolo%20Scavino/Barolo/2019/770287ebba1a31b83c0ab14c97fbb278",
    "wine_type": "still"
  },
  {
    "id": "1301167",
    "winery_full": "Bela",
    "wine_full": "Ribera del Duero",
    "vintage": "2021",
    "note": "An elegant red, with fine tannins enmeshed with flavors of pureed raspberry and black plum reduction, soft fig, thyme and lavender accents, while a minerally underpinning echoes on the finish. Drink now through 2028. 10,000 cases made, 1,000 cases imported.",
    "taster_initials": "AN",
    "color": "Red",
    "country": "Spain",
    "region": "Spain",
    "score": 91,
    "price": 20,
    "alternate_bottle_size": "",
    "issue_date": "45291",
    "top100_year": 2023,
    "top100_rank": 79,
    "label_url": "",
    "wine_type": "still"
  },
  {
    "id": "1300167",
    "winery_full": "Isole & Olena",
    "wine_full": "Toscana Cepparello",
    "vintage": "2020",
    "note": "Expressive and sumptuous from the get-go, this red features cherry, strawberry, rose, orange peel, mineral and Tuscan herb aromas and flavors. Sangiovese. Best from 2025 through 2045. 4,800 cases made, 800 cases imported.",
    "taster_initials": "BS",
    "color": "Red",
    "country": "Italy",
    "region": "Tuscany",
    "score": 96,
    "price": 150,
    "alternate_bottle_size": "",
    "issue_date": "45230",
    "top100_year": 2023,
    "top100_rank": 80,
    "label_url": "https://mshanken-wineapi.imgix.net/Isole%20%26%20Olena/Toscana%20Cepparello/2020/172be08e664c3529415c714698234676",
    "wine_type": "still"
  },
  {
    "id": "1294860",
    "winery_full": "Guillaume Gonnet",
    "wine_full": "Châteauneuf-du-Pape Bel Ami",
    "vintage": "2020",
    "note": "Seductive and pure, with glossy boysenberry and red currant gliding through the round palate. Reveals graphite that lines the palate, with dried thyme and lavender adding lift. This is powered by snappy acidity, which keeps this from being heavy or flat. Grenache, Syrah, Mourvèdre and Cinsault. Drink now through 2035. 20,000 cases made, 10,000 cases imported.",
    "taster_initials": "KB",
    "color": "Red",
    "country": "France",
    "region": "Rhône",
    "score": 92,
    "price": 38,
    "alternate_bottle_size": "",
    "issue_date": "44985",
    "top100_year": 2023,
    "top100_rank": 81,
    "label_url": "https://mshanken-wineapi.imgix.net/Guillaume%20Gonnet/Ch%C3%A2teauneuf-du-Pape%20Bel%20Ami/2020/76733f6ffbabcfce03ce9a318f7d8b94",
    "wine_type": "still"
  },
  {
    "id": "1301654",
    "winery_full": "Dominio del Plata",
    "wine_full": "Susana Balbo Signature Brioso White Uco Valley",
    "vintage": "2022",
    "note": "Offers aromas of gardenia and peach blossoms that leap from the glass, with traces of celery salt and lime zest underneath. Shows vibrant peach and finger lime on the palate, with a nice inlay of chalky minerality adding to the lingering finish. Sémillon, Sauvignon Blanc and Torrontés. Drink now. 2,900 cases made, 700 cases imported.",
    "taster_initials": "AR",
    "color": "White",
    "country": "Argentina",
    "region": "Mendoza",
    "score": 91,
    "price": 24,
    "alternate_bottle_size": "",
    "issue_date": "45260",
    "top100_year": 2023,
    "top100_rank": 82,
    "label_url": "",
    "wine_type": "still"
  },
  {
    "id": "1297219",
    "winery_full": "Morgante",
    "wine_full": "Nero d'Avola Sicilia",
    "vintage": "2020",
    "note": "An elegant, medium-bodied red, with fine tannins and bright acidity framing flavors of wild strawberry, ripe raspberry, anise hyssop and dried thyme, followed by a tar-tinged finish. Drink now through 2028. 25,000 cases made, 2,000 cases imported.",
    "taster_initials": "AN",
    "color": "Red",
    "country": "Italy",
    "region": "Sicily",
    "score": 90,
    "price": 19,
    "alternate_bottle_size": "",
    "issue_date": "45199",
    "top100_year": 2023,
    "top100_rank": 83,
    "label_url": "https://mshanken-wineapi.imgix.net/Morgante/Nero%20d%27Avola%20Sicilia/2020/c7ef5284399ca725a29e577959e2509e",
    "wine_type": "still"
  },
  {
    "id": "1294779",
    "winery_full": "Viña Santa Ema",
    "wine_full": "Carmenère Peumo Amplus One",
    "vintage": "2019",
    "note": "A trace of tarragon lends a slight herbal tinge to this red, which offers a wealth of red currant and linzer torte flavors on a plush, polished frame. Reveals hints of Earl Grey that chime in around fine, mineral-laced tannins. Drink now through 2028. 1,000 cases imported.",
    "taster_initials": "AR",
    "color": "Red",
    "country": "Chile",
    "region": "Rapel",
    "score": 91,
    "price": 30,
    "alternate_bottle_size": "",
    "issue_date": "45046",
    "top100_year": 2023,
    "top100_rank": 84,
    "label_url": "https://mshanken-wineapi.imgix.net/Vi%C3%B1a%20Santa%20Ema/Carmen%C3%A8re%20Peumo%20Amplus%20One/2019/5c29686762c49abe03b90ca181255f9e",
    "wine_type": "still"
  },
  {
    "id": "1301891",
    "winery_full": "Alpha Estate",
    "wine_full": "Sauvignon Blanc Florina",
    "vintage": "2022",
    "note": "A bright, light- to medium-bodied white, with hints of flint and chive blossoms accenting ripe green pear and melon fruit. Well-knit, with a minerally finish. Drink now through 2026. 19,700 cases made, 2,500 cases imported.",
    "taster_initials": "AN",
    "color": "White",
    "country": "Greece",
    "region": "Greece",
    "score": 90,
    "price": 27,
    "alternate_bottle_size": "",
    "issue_date": "45275",
    "top100_year": 2023,
    "top100_rank": 85,
    "label_url": "",
    "wine_type": "still"
  },
  {
    "id": "1297943",
    "winery_full": "Château Jérémie",
    "wine_full": "Corbières",
    "vintage": "2021",
    "note": "There's a refreshing herbaceous lift in this delicious red, which nicely offsets the dense, ripe fruit profile. Cherry, plum and red currant fill out the palate, flecked with smoked meat, violet, forest floor and mineral details. Pencil shavings line the finish, marked by black pepper and smoke. Shows great character and balance. Carignan, Grenache, Syrah and Mourvèdre. Drink now. 2,000 cases made, 500 cases imported.",
    "taster_initials": "KB",
    "color": "Red",
    "country": "France",
    "region": "Languedoc-Roussillon",
    "score": 92,
    "price": 25,
    "alternate_bottle_size": "",
    "issue_date": "45214",
    "top100_year": 2023,
    "top100_rank": 86,
    "label_url": "https://mshanken-wineapi.imgix.net/Ch%C3%A2teau%20J%C3%A9r%C3%A9mie/Corbi%C3%A8res/2021/d67e19f9095cfa72760e2132b487c61b",
    "wine_type": "still"
  },
  {
    "id": "1297023",
    "winery_full": "Fritz Haag",
    "wine_full": "Riesling Kabinett Mosel Brauneberger Juffer",
    "vintage": "2021",
    "note": "Despite the sweetness, this is laser-focused and linear, powered by a lime-edged beam of bracing acidity and refined crushed slate minerality. Builds in concentration to flavors of apple blossoms and honeyed orchard fruit, with a thread of smoke. This has a long life ahead. Drink now through 2035. 2,500 cases made, 266 cases imported.",
    "taster_initials": "KB",
    "color": "White",
    "country": "Germany",
    "region": "Germany",
    "score": 92,
    "price": 29,
    "alternate_bottle_size": "",
    "issue_date": "45169",
    "top100_year": 2023,
    "top100_rank": 87,
    "label_url": "https://mshanken-wineapi.imgix.net/Fritz%20Haag/Riesling%20Kabinett%20Mosel%20Brauneberger%20Juffer/2021/d995a012863a7c089bffc0ece1b0f6d6",
    "wine_type": "still"
  },
  {
    "id": "1297085",
    "winery_full": "Domaine de Mourchon",
    "wine_full": "Côtes du Rhône-Villages Séguret Grande Réserve",
    "vintage": "2020",
    "note": "Alluring and expressive, with beautiful range to the violet, plum and cherry liqueur flavors, all edged in graphite. Delivers impressive harmony and texture, with warm cedar notes rounding out the formidable palate. Reveals slightly grainy tannins that provide a firm frame. Delicious. Grenache and Syrah. Drink now through 2030. 1,500 cases made, 500 cases imported.",
    "taster_initials": "KB",
    "color": "Red",
    "country": "France",
    "region": "Rhône",
    "score": 92,
    "price": 30,
    "alternate_bottle_size": "",
    "issue_date": "45169",
    "top100_year": 2023,
    "top100_rank": 88,
    "label_url": "https://mshanken-wineapi.imgix.net/Domaine%20de%20Mourchon/C%C3%B4tes%20du%20Rh%C3%B4ne-Villages%20S%C3%A9guret%20Grande%20R%C3%A9serve/2020/bc5c57725f56256da27ffba49265cbaf",
    "wine_type": "still"
  },
  {
    "id": "1298717",
    "winery_full": "Pisoni Family",
    "wine_full": "Chardonnay Santa Lucia Highlands Lucia Soberanes Vineyard",
    "vintage": "2021",
    "note": "Supple and elegant, with a fleshy core of peach, white raspberry and lemon curd flavors that are generous and focused. Delivers details of salted butterscotch, lime zest, wild fennel and lemon blossoms, with salty minerality leaving a fresh, detailed finish. Drink now through 2030. 205 cases made.",
    "taster_initials": "MW",
    "color": "White",
    "country": "United States",
    "region": "California",
    "score": 93,
    "price": 65,
    "alternate_bottle_size": "",
    "issue_date": "45138",
    "top100_year": 2023,
    "top100_rank": 89,
    "label_url": "https://mshanken-wineapi.imgix.net/Lucia/Chardonnay%20Santa%20Lucia%20Highlands%20Soberanes%20Vineyard/2021/5823143340957cc0166c5b425e7331f4",
    "wine_type": "still"
  },
  {
    "id": "1296485",
    "winery_full": "Louis Jadot",
    "wine_full": "Corton Pougets Domaine des Héritiers",
    "vintage": "2020",
    "note": "Intense and tightly wound, this red is firmly structured and energetic, featuring cherry, strawberry, stone and spice flavors, with the acidity and tannins lending support for future evolution. All the components are there, this just needs a few years to knit together. Best from 2027 through 2045. 258 cases made, 129 cases imported.",
    "taster_initials": "BS",
    "color": "Red",
    "country": "France",
    "region": "Burgundy",
    "score": 96,
    "price": 150,
    "alternate_bottle_size": "",
    "issue_date": "45077",
    "top100_year": 2023,
    "top100_rank": 90,
    "label_url": "https://mshanken-wineapi.imgix.net/Louis%20Jadot/Corton%20Pougets%20Domaine%20des%20H%C3%A9ritiers/2020/2544cf0a0126ad2b3d6d78736dee4ef7",
    "wine_type": "still"
  },
  {
    "id": "1303437",
    "winery_full": "François Pinon",
    "wine_full": "Vouvray Silex Noir",
    "vintage": "2018",
    "note": "A warm, sunny, seductive white, with a luscious profile to the persimmon, ripe pear, green plum and crushed nectarine flavors. This has a very creamy texture, with a beam of vivid acidity and salty mineral notes keeping it honest. Earthy undertones move through the supple palate with a veil of smoke marking the tangy finish. Drink now through 2032. 1,200 cases made, 450 cases imported.",
    "taster_initials": "KB",
    "color": "White",
    "country": "France",
    "region": "Loire",
    "score": 92,
    "price": 33,
    "alternate_bottle_size": "",
    "issue_date": "45260",
    "top100_year": 2023,
    "top100_rank": 91,
    "label_url": "https://mshanken-wineapi.imgix.net/Fran%C3%A7ois%20Pinon/Vouvray%20Silex%20Noir/2018/2a2197048a2273a9be1886f1eb1c4fef",
    "wine_type": "still"
  },
  {
    "id": "1302329",
    "winery_full": "Chateau de Plaisance",
    "wine_full": "Anjou White Ronceray",
    "vintage": "2021",
    "note": "This shows Chenin's ability to balance ripeness and concentration with structure and polish, with honeyed lemon, glazed mango, warm hay and barley flavors all buoyed by citrusy acidity and savory notes of dried thyme. A quinine kick marks the powerful, tension-filled finish. Drink now through 2030. 650 cases made, 500 cases imported.",
    "taster_initials": "KB",
    "color": "White",
    "country": "France",
    "region": "Loire",
    "score": 92,
    "price": 44,
    "alternate_bottle_size": "",
    "issue_date": "45260",
    "top100_year": 2023,
    "top100_rank": 92,
    "label_url": "https://mshanken-wineapi.imgix.net/Chateau%20de%20Plaisance/Anjou%20White%20Ronceray/2021/f0f241aca9323bd6f80c8932787cfb0c",
    "wine_type": "still"
  },
  {
    "id": "1298794",
    "winery_full": "Pierre Amadieu",
    "wine_full": "Gigondas Le Pas de l'Aigle",
    "vintage": "2020",
    "note": "A wine with a lot of soul and character, this leans slightly modern, with charred apple wood and sweet cedar nicely polishing a core of fig puree and black cherry. The long, harmonious finish glides through, revealing rooibos tea and smoked <em>garrigue</em> details, while a tug of tannins provide a ballast. Grenache and Syrah. Drink now through 2035. 1,700 cases made, 400 cases imported.",
    "taster_initials": "KB",
    "color": "Red",
    "country": "France",
    "region": "Rhône",
    "score": 93,
    "price": 55,
    "alternate_bottle_size": "",
    "issue_date": "45214",
    "top100_year": 2023,
    "top100_rank": 93,
    "label_url": "https://mshanken-wineapi.imgix.net/Pierre%20Amadieu/Gigondas%20Le%20Pas%20de%20l%27Aigle/2020/0075d4ee2c7f1a80b1b26031f58bdff2",
    "wine_type": "still"
  },
  {
    "id": "1297628",
    "winery_full": "Prager",
    "wine_full": "Riesling Federspiel Wachau Steinriegl",
    "vintage": "2021",
    "note": "A juicy wine, with mouthwatering acidity coursing throughout, while beeswax, lanolin and chamomile cascade across the broad palate. Refined and graceful, delivering apple, lime and bitter herbs, with nice fleshiness, mineral power and depth. Drink now through 2035. 1,800 cases made, 125 cases imported.",
    "taster_initials": "KB",
    "color": "White",
    "country": "Austria",
    "region": "Niederösterreich",
    "score": 92,
    "price": 42,
    "alternate_bottle_size": "",
    "issue_date": "45169",
    "top100_year": 2023,
    "top100_rank": 94,
    "label_url": "https://mshanken-wineapi.imgix.net/Prager/Riesling%20Federspiel%20Wachau%20Steinriegl/2021/29b73ad43b18cbe2bb22e37fd314046e",
    "wine_type": "still"
  },
  {
    "id": "1295449",
    "winery_full": "Jean-Luc Colombo",
    "wine_full": "Cornas Les Ruchets",
    "vintage": "2020",
    "note": "Sleek and polished, with a bold cascade of blackberry confit, singed <em>garrigue</em> and warm fig, this is delicious and opulent yet powered by a savory undercurrent. Offers charred cedar that adds depth and roundness to the palate, while the pull of salt and crushed iron offsets the silky, dense character. This has staying power. Best from 2025 through 2032. 660 cases made, 250 cases imported.",
    "taster_initials": "KB",
    "color": "Red",
    "country": "France",
    "region": "Rhône",
    "score": 94,
    "price": 115,
    "alternate_bottle_size": "",
    "issue_date": "45046",
    "top100_year": 2023,
    "top100_rank": 95,
    "label_url": "https://mshanken-wineapi.imgix.net/Jean-Luc%20Colombo/Cornas%20Les%20Ruchets/2020/16a0e95b3136745dee87762d7a7d27dd",
    "wine_type": "still"
  },
  {
    "id": "1301680",
    "winery_full": "Ink Grade",
    "wine_full": "Cabernet Sauvignon Napa Valley",
    "vintage": "2019",
    "note": "Expressive, with bramble and black licorice notes leading off, followed quickly by fresh black cherry and currant preserves. Features flashes of bay leaf and mesquite on the sleek finish, with a strong mineral underpinning as well. Drink now through 2035. 5,600 cases made.",
    "taster_initials": "JM",
    "color": "Red",
    "country": "United States",
    "region": "California",
    "score": 92,
    "price": 120,
    "alternate_bottle_size": "",
    "issue_date": "45245",
    "top100_year": 2023,
    "top100_rank": 96,
    "label_url": "https://mshanken-wineapi.imgix.net/Ink%20Grade/New%20Wine/2019/1be749e75b60132d63b80fb046b11236",
    "wine_type": "still"
  },
  {
    "id": "1294526",
    "winery_full": "Domaine de Marcoux",
    "wine_full": "Châteauneuf-du-Pape White",
    "vintage": "2021",
    "note": "Shows alluring creamed pear and verbena notes that are mouthfilling and rich, yet zesty minerality and vibrant acidity keep the palate fresh. The lengthy finish is marked by floral highlights, dried thyme and a note of brioche. Drink now through 2028. 9,600 cases made, 330 cases imported.",
    "taster_initials": "KB",
    "color": "White",
    "country": "France",
    "region": "Rhône",
    "score": 92,
    "price": 76,
    "alternate_bottle_size": "",
    "issue_date": "44985",
    "top100_year": 2023,
    "top100_rank": 97,
    "label_url": "",
    "wine_type": "still"
  },
  {
    "id": "1297977",
    "winery_full": "Cathiard Family Estate",
    "wine_full": "Founding Brothers Napa Valley",
    "vintage": "2020",
    "note": "This has a good, lively mix of red and black fruit—plum, currant, cherry—that fills out the core, while brambly energy fuels the licorice- and roasted vanilla–accented finish. Stays grounded, thanks to a late tug of earth. Very solid for the vintage. Cabernet Sauvignon, Merlot and Cabernet Franc. Drink now through 2035. 1,250 cases made.",
    "taster_initials": "JM",
    "color": "Red",
    "country": "United States",
    "region": "California",
    "score": 92,
    "price": 225,
    "alternate_bottle_size": "",
    "issue_date": "45245",
    "top100_year": 2023,
    "top100_rank": 98,
    "label_url": "",
    "wine_type": "still"
  },
  {
    "id": "1301561",
    "winery_full": "Fleur de Miraval",
    "wine_full": "Brut Rosé Champagne Petite Fleur",
    "vintage": "NV",
    "note": "An elegant Champagne, offering a fine, lacy mousse and a lively but still delicate frame of acidity for notes of apricot and wild cherry fruit, grated ginger and pink grapefruit zest. Simultaneously, this has an underpinning of toasted nuts, smoke and chalk adding richness and depth. Chardonnay and Pinot Noir. Drink now through 2026. 3,500 cases imported.",
    "taster_initials": "AN",
    "color": "Rosé",
    "country": "France",
    "region": "Champagne",
    "score": 93,
    "price": 110,
    "alternate_bottle_size": "",
    "issue_date": "45260",
    "top100_year": 2023,
    "top100_rank": 99,
    "label_url": "https://mshanken-wineapi.imgix.net/Fleur%20de%20Miraval/Brut%20Ros%C3%A9%20Champagne%20Petite%20Fleur/2023/268d22e3f4bcc48475141c33e39fde20",
    "wine_type": "sparkling"
  },
  {
    "id": "1301728",
    "winery_full": "Morisoli",
    "wine_full": "Cabernet Sauvignon Rutherford",
    "vintage": "2019",
    "note": "This has a fresh, focused core of red currant and black cherry flavors laced with cedar, dusty earth and iron minerality along the way. Fresh, fine-grained and reserved through the finish. Very Rutherford in feel, with the minerality bringing nice precision. Best from 2024 through 2036. 140 cases made.",
    "taster_initials": "JM",
    "color": "Red",
    "country": "United States",
    "region": "California",
    "score": 93,
    "price": 205,
    "alternate_bottle_size": "",
    "issue_date": "45245",
    "top100_year": 2023,
    "top100_rank": 100,
    "label_url": "https://mshanken-wineapi.imgix.net/Morisoli/Cabernet%20Sauvignon%20Rutherford/2019/88f709adb654b4f228a96a3d8cceba39",
    "wine_type": "still"
  }
]